Workbook

Sheet Параметры
A1: ПАРАМЕТРЫ (меняй тут — пересчитается весь лист Юнит)
A2: Курс KRW→RUB | B2: 0.053
A3: Множитель себестоимости | B3: 1.2
A4: СПП | B4: 0.4
A5: Комиссия WB | B5: 0.415
A6: Эквайринг | B6: 0.0235
A7: Налог УСН | B7: 0.06
A8: Обратная логистика, ₽ | B8: 50
A9: Выкуп | B9: 0.9219
A10: Доп. обработка, ₽ | B10: 60
A11: Хранение, ₽ | B11: 0

Sheet Юнит
A1: Бренд | B1: Товар | C1: Баркод | D1: Кол-во заказ | E1: Цена KRW | F1: Себестоимость ₽ | G1: Себестоимость ИТОГО | H1: ПРОДАЖНАЯ ЦЕНА с СПП ₽ | I1: Цена до СПП ₽ | J1: ДРР % | K1: Логистика ₽ | L1: Реклама ₽ | M1: Комиссия ₽ | N1: Эквайринг ₽ | O1: Налог ₽ | P1: Обр.логистика ₽ | Q1: Маржа без ДРР ₽ | R1: Маржа с ДРР ₽ | S1: ROI % | T1: Прибыль ИТОГО
A2: CELIMAX | B2: CELIMAX DUAL BARRIER CREAMY TONER 150ML | C2: 8809606850475 | D2: 25008 | E2: 8930 | F2: =E2*Параметры!$B$2*Параметры!$B$3 | G2: =F2*D2 | H2: 1000 | I2: =IF($H2="","",ROUND(H2/(1-Параметры!$B$4),0)) | J2: 0.05 | K2: 90 | L2: =IF($I2="","",I2*J2) | M2: =IF($I2="","",I2*Параметры!$B$5) | N2: =IF($H2="","",H2*Параметры!$B$6) | O2: =IF($I2="","",I2*Параметры!$B$7) | P2: =ROUND(Параметры!$B$8*(1-Параметры!$B$9),1) | Q2: =IF($I2="","",I2-M2-K2-N2-O2-P2-Параметры!$B$10-Параметры!$B$11-F2) | R2: =IF($I2="","",Q2-L2) | S2: =IF(OR($H2="",F2=0),"",ROUND(R2/F2*100,1)) | T2: =R2*D2
A3: CELIMAX | B3: CELIMAX JI WOO GAE HEARTLEAF BHA PEELING PAD 60PADS | C3: 8809463992615 | D3: 1200 | E3: 7350 | F3: =E3*Параметры!$B$2*Параметры!$B$3 | G3: =F3*D3 | H3: 1792 | I3: =IF($H3="","",ROUND(H3/(1-Параметры!$B$4),0)) | J3: 0.1 | K3: 90 | L3: =IF($I3="","",I3*J3) | M3: =IF($I3="","",I3*Параметры!$B$5) | N3: =IF($H3="","",H3*Параметры!$B$6) | O3: =IF($I3="","",I3*Параметры!$B$7) | P3: =ROUND(Параметры!$B$8*(1-Параметры!$B$9),1) | Q3: =IF($I3="","",I3-M3-K3-N3-O3-P3-Параметры!$B$10-Параметры!$B$11-F3) | R3: =IF($I3="","",Q3-L3) | S3: =IF(OR($H3="",F3=0),"",ROUND(R3/F3*100,1)) | T3: =R3*D3
A4: CELIMAX | B4: CELIMAX THE REAL NONI STARTER KIT | C4: 8809971482349 | D4: 480 | E4: 7600 | F4: =E4*Параметры!$B$2*Параметры!$B$3 | G4: =F4*D4 | H4: 1204 | I4: =IF($H4="","",ROUND(H4/(1-Параметры!$B$4),0)) | J4: 0.1 | K4: 90 | L4: =IF($I4="","",I4*J4) | M4: =IF($I4="","",I4*Параметры!$B$5) | N4: =IF($H4="","",H4*Параметры!$B$6) | O4: =IF($I4="","",I4*Параметры!$B$7) | P4: =ROUND(Параметры!$B$8*(1-Параметры!$B$9),1) | Q4: =IF($I4="","",I4-M4-K4-N4-O4-P4-Параметры!$B$10-Параметры!$B$11-F4) | R4: =IF($I4="","",Q4-L4) | S4: =IF(OR($H4="",F4=0),"",ROUND(R4/F4*100,1)) | T4: =R4*D4
A5: CELIMAX | B5: CELIMAX DUAL BARRIER TRIAL KIT | C5: 8809606852332 | D5: 448 | E5: 5400 | F5: =E5*Параметры!$B$2*Параметры!$B$3 | G5: =F5*D5 | H5: 898 | I5: =IF($H5="","",ROUND(H5/(1-Параметры!$B$4),0)) | J5: 0.1 | K5: 90 | L5: =IF($I5="","",I5*J5) | M5: =IF($I5="","",I5*Параметры!$B$5) | N5: =IF($H5="","",H5*Параметры!$B$6) | O5: =IF($I5="","",I5*Параметры!$B$7) | P5: =ROUND(Параметры!$B$8*(1-Параметры!$B$9),1) | Q5: =IF($I5="","",I5-M5-K5-N5-O5-P5-Параметры!$B$10-Параметры!$B$11-F5) | R5: =IF($I5="","",Q5-L5) | S5: =IF(OR($H5="",F5=0),"",ROUND(R5/F5*100,1)) | T5: =R5*D5
A6: CELIMAX | B6: CELIMAX THE REAL NONI ACNE BUBBLE CLEANSER 155ML | C6: 8809541379468 | D6: 312 | E6: 6550 | F6: =E6*Параметры!$B$2*Параметры!$B$3 | G6: =F6*D6 | H6: 1190 | I6: =IF($H6="","",ROUND(H6/(1-Параметры!$B$4),0)) | J6: 0.1 | K6: 90 | L6: =IF($I6="","",I6*J6) | M6: =IF($I6="","",I6*Параметры!$B$5) | N6: =IF($H6="","",H6*Параметры!$B$6) | O6: =IF($I6="","",I6*Параметры!$B$7) | P6: =ROUND(Параметры!$B$8*(1-Параметры!$B$9),1) | Q6: =IF($I6="","",I6-M6-K6-N6-O6-P6-Параметры!$B$10-Параметры!$B$11-F6) | R6: =IF($I6="","",Q6-L6) | S6: =IF(OR($H6="",F6=0),"",ROUND(R6/F6*100,1)) | T6: =R6*D6
A7: CELIMAX | B7: CELIMAX DERMA NATURE FRESH BLACKHEAD JOJOBA CLEANSING OIL 150ML | C7: 8806050298525 | D7: 315 | E7: 7100 | F7: =E7*Параметры!$B$2*Параметры!$B$3 | G7: =F7*D7 | H7: 1300 | I7: =IF($H7="","",ROUND(H7/(1-Параметры!$B$4),0)) | J7: 0.1 | K7: 90 | L7: =IF($I7="","",I7*J7) | M7: =IF($I7="","",I7*Параметры!$B$5) | N7: =IF($H7="","",H7*Параметры!$B$6) | O7: =IF($I7="","",I7*Параметры!$B$7) | P7: =ROUND(Параметры!$B$8*(1-Параметры!$B$9),1) | Q7: =IF($I7="","",I7-M7-K7-N7-O7-P7-Параметры!$B$10-Параметры!$B$11-F7) | R7: =IF($I7="","",Q7-L7) | S7: =IF(OR($H7="",F7=0),"",ROUND(R7/F7*100,1)) | T7: =R7*D7
A8: CELIMAX | B8: CELIMAX THE REAL NONI CALMING GLOW PAD 50EA | C8: 8809750465464 | D8: 984 | E8: 8550 | F8: =E8*Параметры!$B$2*Параметры!$B$3 | G8: =F8*D8 | H8: 1792 | I8: =IF($H8="","",ROUND(H8/(1-Параметры!$B$4),0)) | J8: 0.1 | K8: 90 | L8: =IF($I8="","",I8*J8) | M8: =IF($I8="","",I8*Параметры!$B$5) | N8: =IF($H8="","",H8*Параметры!$B$6) | O8: =IF($I8="","",I8*Параметры!$B$7) | P8: =ROUND(Параметры!$B$8*(1-Параметры!$B$9),1) | Q8: =IF($I8="","",I8-M8-K8-N8-O8-P8-Параметры!$B$10-Параметры!$B$11-F8) | R8: =IF($I8="","",Q8-L8) | S8: =IF(OR($H8="",F8=0),"",ROUND(R8/F8*100,1)) | T8: =R8*D8
A9: CELIMAX | B9: CELIMAX THE REAL CICA SOOTHING CREAM 50ML | C9: 8809782557861 | D9: 1200 | E9: 8080 | F9: =E9*Параметры!$B$2*Параметры!$B$3 | G9: =F9*D9 | H9: 1304 | I9: =IF($H9="","",ROUND(H9/(1-Параметры!$B$4),0)) | J9: 0.1 | K9: 90 | L9: =IF($I9="","",I9*J9) | M9: =IF($I9="","",I9*Параметры!$B$5) | N9: =IF($H9="","",H9*Параметры!$B$6) | O9: =IF($I9="","",I9*Параметры!$B$7) | P9: =ROUND(Параметры!$B$8*(1-Параметры!$B$9),1) | Q9: =IF($I9="","",I9-M9-K9-N9-O9-P9-Параметры!$B$10-Параметры!$B$11-F9) | R9: =IF($I9="","",Q9-L9) | S9: =IF(OR($H9="",F9=0),"",ROUND(R9/F9*100,1)) | T9: =R9*D9
A10: CELIMAX | B10: CELIMAX THE REAL CICA NIACINAMIDE AC CALMING SERUM 40ML | C10: 8809743544626 | D10: 864 | E10: 9930 | F10: =E10*Параметры!$B$2*Параметры!$B$3 | G10: =F10*D10 | H10: 1552 | I10: =IF($H10="","",ROUND(H10/(1-Параметры!$B$4),0)) | J10: 0.1 | K10: 90 | L10: =IF($I10="","",I10*J10) | M10: =IF($I10="","",I10*Параметры!$B$5) | N10: =IF($H10="","",H10*Параметры!$B$6) | O10: =IF($I10="","",I10*Параметры!$B$7) | P10: =ROUND(Параметры!$B$8*(1-Параметры!$B$9),1) | Q10: =IF($I10="","",I10-M10-K10-N10-O10-P10-Параметры!$B$10-Параметры!$B$11-F10) | R10: =IF($I10="","",Q10-L10) | S10: =IF(OR($H10="",F10=0),"",ROUND(R10/F10*100,1)) | T10: =R10*D10
A11: CELIMAX | B11: CELIMAX THE REAL NONI ENERGY REPAIR CREAM 50ML | C11: 8809686386185 | D11: 720 | E11: 11540 | F11: =E11*Параметры!$B$2*Параметры!$B$3 | G11: =F11*D11 | H11: 1684 | I11: =IF($H11="","",ROUND(H11/(1-Параметры!$B$4),0)) | J11: 0.1 | K11: 90 | L11: =IF($I11="","",I11*J11) | M11: =IF($I11="","",I11*Параметры!$B$5) | N11: =IF($H11="","",H11*Параметры!$B$6) | O11: =IF($I11="","",I11*Параметры!$B$7) | P11: =ROUND(Параметры!$B$8*(1-Параметры!$B$9),1) | Q11: =IF($I11="","",I11-M11-K11-N11-O11-P11-Параметры!$B$10-Параметры!$B$11-F11) | R11: =IF($I11="","",Q11-L11) | S11: =IF(OR($H11="",F11=0),"",ROUND(R11/F11*100,1)) | T11: =R11*D11
A12: CELIMAX | B12: CELIMAX OIL CONTROL MOISTURIZING CREAM 80ML | C12: 8809743546880 | D12: 600 | E12: 9470 | F12: =E12*Параметры!$B$2*Параметры!$B$3 | G12: =F12*D12 | H12: 1722 | I12: =IF($H12="","",ROUND(H12/(1-Параметры!$B$4),0)) | J12: 0.1 | K12: 90 | L12: =IF($I12="","",I12*J12) | M12: =IF($I12="","",I12*Параметры!$B$5) | N12: =IF($H12="","",H12*Параметры!$B$6) | O12: =IF($I12="","",I12*Параметры!$B$7) | P12: =ROUND(Параметры!$B$8*(1-Параметры!$B$9),1) | Q12: =IF($I12="","",I12-M12-K12-N12-O12-P12-Параметры!$B$10-Параметры!$B$11-F12) | R12: =IF($I12="","",Q12-L12) | S12: =IF(OR($H12="",F12=0),"",ROUND(R12/F12*100,1)) | T12: =R12*D12
A13: CELIMAX | B13: CELIMAX PORE+DARK SPOT BRIGHTENING KIT | C13: 8800296551789 | D13: 576 | E13: 6370 | F13: =E13*Параметры!$B$2*Параметры!$B$3 | G13: =F13*D13 | H13: 1277 | I13: =IF($H13="","",ROUND(H13/(1-Параметры!$B$4),0)) | J13: 0.1 | K13: 90 | L13: =IF($I13="","",I13*J13) | M13: =IF($I13="","",I13*Параметры!$B$5) | N13: =IF($H13="","",H13*Параметры!$B$6) | O13: =IF($I13="","",I13*Параметры!$B$7) | P13: =ROUND(Параметры!$B$8*(1-Параметры!$B$9),1) | Q13: =IF($I13="","",I13-M13-K13-N13-O13-P13-Параметры!$B$10-Параметры!$B$11-F13) | R13: =IF($I13="","",Q13-L13) | S13: =IF(OR($H13="",F13=0),"",ROUND(R13/F13*100,1)) | T13: =R13*D13
... A53: Manyo | B53: BIFIDA BIOME AMPOULE TONER 210ml | C53: 8809730950881 | D53: 1200 | E53: 5850 | F53: =E53*Параметры!$B$2*Параметры!$B$3 | G53: =F53*D53 | H53: 1332 | I53: =IF($H53="","",ROUND(H53/(1-Параметры!$B$4),0)) | J53: 0.1 | K53: 90 | L53: =IF($I53="","",I53*J53) | M53: =IF($I53="","",I53*Параметры!$B$5) | N53: =IF($H53="","",H53*Параметры!$B$6) | O53: =IF($I53="","",I53*Параметры!$B$7) | P53: =ROUND(Параметры!$B$8*(1-Параметры!$B$9),1) | Q53: =IF($I53="","",I53-M53-K53-N53-O53-P53-Параметры!$B$10-Параметры!$B$11-F53) | R53: =IF($I53="","",Q53-L53) | S53: =IF(OR($H53="",F53=0),"",ROUND(R53/F53*100,1)) | T53: =R53*D53
A54: ENOUGH | B54: ENOUGH Premium Ultra X10 cover up Collagen foundation #21 [100ml] | D54: 200 | E54: 3880 | F54: =E54*Параметры!$B$2*Параметры!$B$3 | G54: =F54*D54 | H54: 681 | I54: =IF($H54="","",ROUND(H54/(1-Параметры!$B$4),0)) | J54: 0.1 | K54: 90 | L54: =IF($I54="","",I54*J54) | M54: =IF($I54="","",I54*Параметры!$B$5) | N54: =IF($H54="","",H54*Параметры!$B$6) | O54: =IF($I54="","",I54*Параметры!$B$7) | P54: =ROUND(Параметры!$B$8*(1-Параметры!$B$9),1) | Q54: =IF($I54="","",I54-M54-K54-N54-O54-P54-Параметры!$B$10-Параметры!$B$11-F54) | R54: =IF($I54="","",Q54-L54) | S54: =IF(OR($H54="",F54=0),"",ROUND(R54/F54*100,1)) | T54: =R54*D54
A55: Im | B55: Im Sorry for My Skin AGE Capture Firming Enriched Cream [50g] | D55: 880 | E55: 6840 | F55: =E55*Параметры!$B$2*Параметры!$B$3 | G55: =F55*D55 | H55: 1110 | I55: =IF($H55="","",ROUND(H55/(1-Параметры!$B$4),0)) | J55: 0.1 | K55: 90 | L55: =IF($I55="","",I55*J55) | M55: =IF($I55="","",I55*Параметры!$B$5) | N55: =IF($H55="","",H55*Параметры!$B$6) | O55: =IF($I55="","",I55*Параметры!$B$7) | P55: =ROUND(Параметры!$B$8*(1-Параметры!$B$9),1) | Q55: =IF($I55="","",I55-M55-K55-N55-O55-P55-Параметры!$B$10-Параметры!$B$11-F55) | R55: =IF($I55="","",Q55-L55) | S55: =IF(OR($H55="",F55=0),"",ROUND(R55/F55*100,1)) | T55: =R55*D55
A56: Im | B56: Im Sorry for My Skin AGE Capture Hydrating Cream [50g] | D56: 880 | E56: 6840 | F56: =E56*Параметры!$B$2*Параметры!$B$3 | G56: =F56*D56 | H56: 1110 | I56: =IF($H56="","",ROUND(H56/(1-Параметры!$B$4),0)) | J56: 0.1 | K56: 90 | L56: =IF($I56="","",I56*J56) | M56: =IF($I56="","",I56*Параметры!$B$5) | N56: =IF($H56="","",H56*Параметры!$B$6) | O56: =IF($I56="","",I56*Параметры!$B$7) | P56: =ROUND(Параметры!$B$8*(1-Параметры!$B$9),1) | Q56: =IF($I56="","",I56-M56-K56-N56-O56-P56-Параметры!$B$10-Параметры!$B$11-F56) | R56: =IF($I56="","",Q56-L56) | S56: =IF(OR($H56="",F56=0),"",ROUND(R56/F56*100,1)) | T56: =R56*D56
A57: Im | B57: Im Sorry for My Skin AGE Capture Skin Relief Cream [50g] | D57: 480 | E57: 6840 | F57: =E57*Параметры!$B$2*Параметры!$B$3 | G57: =F57*D57 | H57: 1110 | I57: =IF($H57="","",ROUND(H57/(1-Параметры!$B$4),0)) | J57: 0.1 | K57: 90 | L57: =IF($I57="","",I57*J57) | M57: =IF($I57="","",I57*Параметры!$B$5) | N57: =IF($H57="","",H57*Параметры!$B$6) | O57: =IF($I57="","",I57*Параметры!$B$7) | P57: =ROUND(Параметры!$B$8*(1-Параметры!$B$9),1) | Q57: =IF($I57="","",I57-M57-K57-N57-O57-P57-Параметры!$B$10-Параметры!$B$11-F57) | R57: =IF($I57="","",Q57-L57) | S57: =IF(OR($H57="",F57=0),"",ROUND(R57/F57*100,1)) | T57: =R57*D57
A58: Im | B58: Im Sorry for My Skin AGE Capture Vitalizer Cream [50g] | D58: 480 | E58: 6840 | F58: =E58*Параметры!$B$2*Параметры!$B$3 | G58: =F58*D58 | H58: 1110 | I58: =IF($H58="","",ROUND(H58/(1-Параметры!$B$4),0)) | J58: 0.1 | K58: 90 | L58: =IF($I58="","",I58*J58) | M58: =IF($I58="","",I58*Параметры!$B$5) | N58: =IF($H58="","",H58*Параметры!$B$6) | O58: =IF($I58="","",I58*Параметры!$B$7) | P58: =ROUND(Параметры!$B$8*(1-Параметры!$B$9),1) | Q58: =IF($I58="","",I58-M58-K58-N58-O58-P58-Параметры!$B$10-Параметры!$B$11-F58) | R58: =IF($I58="","",Q58-L58) | S58: =IF(OR($H58="",F58=0),"",ROUND(R58/F58*100,1)) | T58: =R58*D58
A59: ENOUGH | B59: ENOUGH Gold snail moisture foundation #13 [100ml] | D59: 1800 | E59: 2839 | F59: =E59*Параметры!$B$2*Параметры!$B$3 | G59: =F59*D59 | H59: 650 | I59: =IF($H59="","",ROUND(H59/(1-Параметры!$B$4),0)) | J59: 0.1 | K59: 90 | L59: =IF($I59="","",I59*J59) | M59: =IF($I59="","",I59*Параметры!$B$5) | N59: =IF($H59="","",H59*Параметры!$B$6) | O59: =IF($I59="","",I59*Параметры!$B$7) | P59: =ROUND(Параметры!$B$8*(1-Параметры!$B$9),1) | Q59: =IF($I59="","",I59-M59-K59-N59-O59-P59-Параметры!$B$10-Параметры!$B$11-F59) | R59: =IF($I59="","",Q59-L59) | S59: =IF(OR($H59="",F59=0),"",ROUND(R59/F59*100,1)) | T59: =R59*D59
A60: ENOUGH | B60: ENOUGH Gold snail moisture foundation #21 [100ml] | D60: 1200 | E60: 2839 | F60: =E60*Параметры!$B$2*Параметры!$B$3 | G60: =F60*D60 | H60: 650 | I60: =IF($H60="","",ROUND(H60/(1-Параметры!$B$4),0)) | J60: 0.1 | K60: 90 | L60: =IF($I60="","",I60*J60) | M60: =IF($I60="","",I60*Параметры!$B$5) | N60: =IF($H60="","",H60*Параметры!$B$6) | O60: =IF($I60="","",I60*Параметры!$B$7) | P60: =ROUND(Параметры!$B$8*(1-Параметры!$B$9),1) | Q60: =IF($I60="","",I60-M60-K60-N60-O60-P60-Параметры!$B$10-Параметры!$B$11-F60) | R60: =IF($I60="","",Q60-L60) | S60: =IF(OR($H60="",F60=0),"",ROUND(R60/F60*100,1)) | T60: =R60*D60
A61: ENOUGH | B61: ENOUGH Collagen moisture foundation #13 [100ml] | D61: 6000 | E61: 2786 | F61: =E61*Параметры!$B$2*Параметры!$B$3 | G61: =F61*D61 | H61: 650 | I61: =IF($H61="","",ROUND(H61/(1-Параметры!$B$4),0)) | J61: 0.1 | K61: 90 | L61: =IF($I61="","",I61*J61) | M61: =IF($I61="","",I61*Параметры!$B$5) | N61: =IF($H61="","",H61*Параметры!$B$6) | O61: =IF($I61="","",I61*Параметры!$B$7) | P61: =ROUND(Параметры!$B$8*(1-Параметры!$B$9),1) | Q61: =IF($I61="","",I61-M61-K61-N61-O61-P61-Параметры!$B$10-Параметры!$B$11-F61) | R61: =IF($I61="","",Q61-L61) | S61: =IF(OR($H61="",F61=0),"",ROUND(R61/F61*100,1)) | T61: =R61*D61
A62: ENOUGH | B62: ENOUGH Collagen moisture foundation #21 [100ml] | D62: 3000 | E62: 2786 | F62: =E62*Параметры!$B$2*Параметры!$B$3 | G62: =F62*D62 | H62: 650 | I62: =IF($H62="","",ROUND(H62/(1-Параметры!$B$4),0)) | J62: 0.1 | K62: 90 | L62: =IF($I62="","",I62*J62) | M62: =IF($I62="","",I62*Параметры!$B$5) | N62: =IF($H62="","",H62*Параметры!$B$6) | O62: =IF($I62="","",I62*Параметры!$B$7) | P62: =ROUND(Параметры!$B$8*(1-Параметры!$B$9),1) | Q62: =IF($I62="","",I62-M62-K62-N62-O62-P62-Параметры!$B$10-Параметры!$B$11-F62) | R62: =IF($I62="","",Q62-L62) | S62: =IF(OR($H62="",F62=0),"",ROUND(R62/F62*100,1)) | T62: =R62*D62
A63: ENOUGH | B63: ENOUGH Collagen moisture foundation #23 [100ml] | D63: 1000 | E63: 2786 | F63: =E63*Параметры!$B$2*Параметры!$B$3 | G63: =F63*D63 | H63: 681 | I63: =IF($H63="","",ROUND(H63/(1-Параметры!$B$4),0)) | J63: 0.1 | K63: 90 | L63: =IF($I63="","",I63*J63) | M63: =IF($I63="","",I63*Параметры!$B$5) | N63: =IF($H63="","",H63*Параметры!$B$6) | O63: =IF($I63="","",I63*Параметры!$B$7) | P63: =ROUND(Параметры!$B$8*(1-Параметры!$B$9),1) | Q63: =IF($I63="","",I63-M63-K63-N63-O63-P63-Параметры!$B$10-Параметры!$B$11-F63) | R63: =IF($I63="","",Q63-L63) | S63: =IF(OR($H63="",F63=0),"",ROUND(R63/F63*100,1)) | T63: =R63*D63
A64: ENOUGH | B64: ENOUGH Premium Ultra X10 cover up Collagen foundation #21 [100ml] | D64: 600 | E64: 3560 | F64: =E64*Параметры!$B$2*Параметры!$B$3 | G64: =F64*D64 | H64: 681 | I64: =IF($H64="","",ROUND(H64/(1-Параметры!$B$4),0)) | J64: 0.1 | K64: 90 | L64: =IF($I64="","",I64*J64) | M64: =IF($I64="","",I64*Параметры!$B$5) | N64: =IF($H64="","",H64*Параметры!$B$6) | O64: =IF($I64="","",I64*Параметры!$B$7) | P64: =ROUND(Параметры!$B$8*(1-Параметры!$B$9),1) | Q64: =IF($I64="","",I64-M64-K64-N64-O64-P64-Параметры!$B$10-Параметры!$B$11-F64) | R64: =IF($I64="","",Q64-L64) | S64: =IF(OR($H64="",F64=0),"",ROUND(R64/F64*100,1)) | T64: =R64*D64
A65: ENOUGH | B65: ENOUGH Premium Rich Gold Double Wear Radiance Foundation #13 [100ml] | D65: 900 | E65: 3676 | F65: =E65*Параметры!$B$2*Параметры!$B$3 | G65: =F65*D65 | H65: 681 | I65: =IF($H65="","",ROUND(H65/(1-Параметры!$B$4),0)) | J65: 0.1 | K65: 90 | L65: =IF($I65="","",I65*J65) | M65: =IF($I65="","",I65*Параметры!$B$5) | N65: =IF($H65="","",H65*Параметры!$B$6) | O65: =IF($I65="","",I65*Параметры!$B$7) | P65: =ROUND(Параметры!$B$8*(1-Параметры!$B$9),1) | Q65: =IF($I65="","",I65-M65-K65-N65-O65-P65-Параметры!$B$10-Параметры!$B$11-F65) | R65: =IF($I65="","",Q65-L65) | S65: =IF(OR($H65="",F65=0),"",ROUND(R65/F65*100,1)) | T65: =R65*D65
... A68: ENOUGH | B68: ENOUGH Collagen Whitening moisture foundation #13 [100ml] | D68: 400 | E68: 2955 | F68: =E68*Параметры!$B$2*Параметры!$B$3 | G68: =F68*D68 | H68: 681 | I68: =IF($H68="","",ROUND(H68/(1-Параметры!$B$4),0)) | J68: 0.1 | K68: 90 | L68: =IF($I68="","",I68*J68) | M68: =IF($I68="","",I68*Параметры!$B$5) | N68: =IF($H68="","",H68*Параметры!$B$6) | O68: =IF($I68="","",I68*Параметры!$B$7) | P68: =ROUND(Параметры!$B$8*(1-Параметры!$B$9),1) | Q68: =IF($I68="","",I68-M68-K68-N68-O68-P68-Параметры!$B$10-Параметры!$B$11-F68) | R68: =IF($I68="","",Q68-L68) | S68: =IF(OR($H68="",F68=0),"",ROUND(R68/F68*100,1)) | T68: =R68*D68
G69: =SUM(G2:G68) | T69: =SUM(T2:T68)

Sheet По брендам
A1: Бренд | B1: Позиций | C1: Кол-во, шт | D1: Себестоимость ИТОГО, ₽ | E1: Прибыль ИТОГО, ₽ | F1: ROI по бренду, % | G1: Доля в прибыли, %
A2: CELIMAX | B2: =COUNTIF('Юнит'!$A$2:$A$68,$A2) | C2: =SUMIF('Юнит'!$A$2:$A$68,$A2,'Юнит'!$D$2:$D$68) | D2: =SUMIF('Юнит'!$A$2:$A$68,$A2,'Юнит'!$G$2:$G$68) | E2: =SUMIF('Юнит'!$A$2:$A$68,$A2,'Юнит'!$T$2:$T$68) | F2: =IF(D2=0,"",ROUND(E2/D2*100,1)) | G2: =IF($E$11=0,"",ROUND(E2/$E$11*100,1))
A3: Round Lab | B3: =COUNTIF('Юнит'!$A$2:$A$68,$A3) | C3: =SUMIF('Юнит'!$A$2:$A$68,$A3,'Юнит'!$D$2:$D$68) | D3: =SUMIF('Юнит'!$A$2:$A$68,$A3,'Юнит'!$G$2:$G$68) | E3: =SUMIF('Юнит'!$A$2:$A$68,$A3,'Юнит'!$T$2:$T$68) | F3: =IF(D3=0,"",ROUND(E3/D3*100,1)) | G3: =IF($E$11=0,"",ROUND(E3/$E$11*100,1))
A4: SKIN1004 | B4: =COUNTIF('Юнит'!$A$2:$A$68,$A4) | C4: =SUMIF('Юнит'!$A$2:$A$68,$A4,'Юнит'!$D$2:$D$68) | D4: =SUMIF('Юнит'!$A$2:$A$68,$A4,'Юнит'!$G$2:$G$68) | E4: =SUMIF('Юнит'!$A$2:$A$68,$A4,'Юнит'!$T$2:$T$68) | F4: =IF(D4=0,"",ROUND(E4/D4*100,1)) | G4: =IF($E$11=0,"",ROUND(E4/$E$11*100,1))
A5: MEDICUBE | B5: =COUNTIF('Юнит'!$A$2:$A$68,$A5) | C5: =SUMIF('Юнит'!$A$2:$A$68,$A5,'Юнит'!$D$2:$D$68) | D5: =SUMIF('Юнит'!$A$2:$A$68,$A5,'Юнит'!$G$2:$G$68) | E5: =SUMIF('Юнит'!$A$2:$A$68,$A5,'Юнит'!$T$2:$T$68) | F5: =IF(D5=0,"",ROUND(E5/D5*100,1)) | G5: =IF($E$11=0,"",ROUND(E5/$E$11*100,1))
A6: VT COSMETICS | B6: =COUNTIF('Юнит'!$A$2:$A$68,$A6) | C6: =SUMIF('Юнит'!$A$2:$A$68,$A6,'Юнит'!$D$2:$D$68) | D6: =SUMIF('Юнит'!$A$2:$A$68,$A6,'Юнит'!$G$2:$G$68) | E6: =SUMIF('Юнит'!$A$2:$A$68,$A6,'Юнит'!$T$2:$T$68) | F6: =IF(D6=0,"",ROUND(E6/D6*100,1)) | G6: =IF($E$11=0,"",ROUND(E6/$E$11*100,1))
A7: DERMA FACTORY | B7: =COUNTIF('Юнит'!$A$2:$A$68,$A7) | C7: =SUMIF('Юнит'!$A$2:$A$68,$A7,'Юнит'!$D$2:$D$68) | D7: =SUMIF('Юнит'!$A$2:$A$68,$A7,'Юнит'!$G$2:$G$68) | E7: =SUMIF('Юнит'!$A$2:$A$68,$A7,'Юнит'!$T$2:$T$68) | F7: =IF(D7=0,"",ROUND(E7/D7*100,1)) | G7: =IF($E$11=0,"",ROUND(E7/$E$11*100,1))
A8: Manyo | B8: =COUNTIF('Юнит'!$A$2:$A$68,$A8) | C8: =SUMIF('Юнит'!$A$2:$A$68,$A8,'Юнит'!$D$2:$D$68) | D8: =SUMIF('Юнит'!$A$2:$A$68,$A8,'Юнит'!$G$2:$G$68) | E8: =SUMIF('Юнит'!$A$2:$A$68,$A8,'Юнит'!$T$2:$T$68) | F8: =IF(D8=0,"",ROUND(E8/D8*100,1)) | G8: =IF($E$11=0,"",ROUND(E8/$E$11*100,1))
A9: ENOUGH | B9: =COUNTIF('Юнит'!$A$2:$A$68,$A9) | C9: =SUMIF('Юнит'!$A$2:$A$68,$A9,'Юнит'!$D$2:$D$68) | D9: =SUMIF('Юнит'!$A$2:$A$68,$A9,'Юнит'!$G$2:$G$68) | E9: =SUMIF('Юнит'!$A$2:$A$68,$A9,'Юнит'!$T$2:$T$68) | F9: =IF(D9=0,"",ROUND(E9/D9*100,1)) | G9: =IF($E$11=0,"",ROUND(E9/$E$11*100,1))
A10: Im | B10: =COUNTIF('Юнит'!$A$2:$A$68,$A10) | C10: =SUMIF('Юнит'!$A$2:$A$68,$A10,'Юнит'!$D$2:$D$68) | D10: =SUMIF('Юнит'!$A$2:$A$68,$A10,'Юнит'!$G$2:$G$68) | E10: =SUMIF('Юнит'!$A$2:$A$68,$A10,'Юнит'!$T$2:$T$68) | F10: =IF(D10=0,"",ROUND(E10/D10*100,1)) | G10: =IF($E$11=0,"",ROUND(E10/$E$11*100,1))
A11: ИТОГО | B11: =SUM(B2:B10) | C11: =SUM(C2:C10) | D11: =SUM(D2:D10) | E11: =SUM(E2:E10) | F11: =IF(D11=0,"",ROUND(E11/D11*100,1)) | G11: 100
