Workbook

Sheet Юнитка FBO
A1: ПАРАМЕТРЫ — меняй жёлтые ячейки, всё пересчитается
A3: Налог с оборота | G3: 0.07
A4: Эквайринг | G4: 0.015
A5: Фулфилмент, ₽/шт | G5: 60
A6: Хранение, ₽/л/день | G6: 0.16
A7: Дней хранения | G7: 0
A8: Наценка за нелокальные продажи % | G8: 0.02
A9: Кроссдок: обработка (склады/СЦ) ₽/л | G9: 0.75
A10: Кроссдок: перевозка ₽/л (средн. 26 скл.) | G10: 4.423
A11: Подписка, % | G11: 0
A12: Товар | B12: Остаток | C12: Кол-во отзывов нужно | D12: Цена конкурента без СПП | E12: Кол-во продаж конкурент | F12: ДРР конкурент | G12: Цена наша без СПП | H12: СПП, % | I12: Цена с СПП | J12: Себест. | K12: Фулфилмент | L12: База затрат | M12: Комиссия % | N12: Комиссия ₽ | O12: Логистика | P12: Наценка нелок., ₽ | Q12: Доставка до ПВЗ | R12: Эквайринг | S12: Налог | T12: Выкуп % | U12: Обр.лог база | V12: Обр.лог | W12: Объём, л | X12: Хранение | Y12: Кроссдок ср., ₽/ед | Z12: Оплата за клик, % | AA12: Оплата за клик ₽ | AB12: Вывод в топ, % | AC12: Вывод в топ ₽ | AD12: Реклама всего ₽ | AE12: ДРР % | AF12: Маржа до рекл. | AG12: Маржа/шт | AH12: Маржа % цены | AI12: ROI % | AJ12: Цена безубыт. | AK12: Подписка, ₽
A13: ENOUGH - Collagen Moisture Foundation [Tone 13] / Тональный крем для лица с коллагеном 13 тон | B13: 1089 | C13: 500 | D13: 1980 | E13: 195 | F13: 8 | G13: 1800 | H13: 0.45 | I13: =G13*(1-H13) | J13: 216.45 | K13: =$G$5 | L13: =J13+K13 | M13: 0.41 | N13: =G13*M13 | O13: 67 | P13: =G13*$G$8 | Q13: 25 | R13: =G13*$G$4 | S13: =I13*$G$3 | T13: 0.9 | U13: 67 | V13: =U13*(1-T13) | W13: 0.4 | X13: =$G$6*$G$7*W13 | Y13: =W13*($G$9+$G$10) | Z13: 0.07 | AA13: =G13*Z13 | AB13: 0.08 | AC13: =G13*AB13 | AD13: =AA13+AC13 | AE13: =AD13/G13 | AF13: =G13-N13-O13-P13-Q13-R13-S13-V13-X13-Y13-L13-AK13 | AG13: =AF13-AD13 | AH13: =AG13/G13 | AI13: =AG13/L13 | AJ13: =(O13+Q13+V13+X13+Y13+L13)/(1-(M13+$G$4+(1-H13)*$G$3+$G$8+$G$11+Z13+AB13)) | AK13: =G13*$G$11
A14: ENOUGH - Collagen Moisture Foundation [Tone 21] / Тональный крем для лица с коллагеном 21 тон | B14: 2275 | C14: 500 | D14: 1910 | E14: 121 | F14: 7.3 | G14: 1800 | H14: 0.45 | I14: =G14*(1-H14) | J14: 242.88 | K14: =$G$5 | L14: =J14+K14 | M14: 0.41 | N14: =G14*M14 | O14: 67 | P14: =G14*$G$8 | Q14: 25 | R14: =G14*$G$4 | S14: =I14*$G$3 | T14: 0.9 | U14: 67 | V14: =U14*(1-T14) | W14: 0.4 | X14: =$G$6*$G$7*W14 | Y14: =W14*($G$9+$G$10) | Z14: 0.07 | AA14: =G14*Z14 | AB14: 0.08 | AC14: =G14*AB14 | AD14: =AA14+AC14 | AE14: =AD14/G14 | AF14: =G14-N14-O14-P14-Q14-R14-S14-V14-X14-Y14-L14-AK14 | AG14: =AF14-AD14 | AH14: =AG14/G14 | AI14: =AG14/L14 | AJ14: =(O14+Q14+V14+X14+Y14+L14)/(1-(M14+$G$4+(1-H14)*$G$3+$G$8+$G$11+Z14+AB14)) | AK14: =G14*$G$11
A15: ETUDE - Baking Powder Crunch Pore Scrub [200ml] / Очищающий скраб для лица с содой | B15: 7910 | C15: 300 | D15: 1730 | E15: 300 | F15: 5 | G15: 1650 | H15: 0.45 | I15: =G15*(1-H15) | J15: 361.03 | K15: =$G$5 | L15: =J15+K15 | M15: 0.41 | N15: =G15*M15 | O15: 67 | P15: =G15*$G$8 | Q15: 25 | R15: =G15*$G$4 | S15: =I15*$G$3 | T15: 0.9 | U15: 67 | V15: =U15*(1-T15) | W15: 0.56 | X15: =$G$6*$G$7*W15 | Y15: =W15*($G$9+$G$10) | Z15: 0.05 | AA15: =G15*Z15 | AB15: 0.05 | AC15: =G15*AB15 | AD15: =AA15+AC15 | AE15: =AD15/G15 | AF15: =G15-N15-O15-P15-Q15-R15-S15-V15-X15-Y15-L15-AK15 | AG15: =AF15-AD15 | AH15: =AG15/G15 | AI15: =AG15/L15 | AJ15: =(O15+Q15+V15+X15+Y15+L15)/(1-(M15+$G$4+(1-H15)*$G$3+$G$8+$G$11+Z15+AB15)) | AK15: =G15*$G$11
A16: FARMSTAY COLLAGEN&HYALURONIC ACID ALL-IN ONE | B16: 6611 | C16: 200 | D16: 3850 | E16: 127 | F16: 6 | G16: 3500 | H16: 0.45 | I16: =G16*(1-H16) | J16: 347.76 | K16: =$G$5 | L16: =J16+K16 | M16: 0.41 | N16: =G16*M16 | O16: 67 | P16: =G16*$G$8 | Q16: 25 | R16: =G16*$G$4 | S16: =I16*$G$3 | T16: 0.9 | U16: 67 | V16: =U16*(1-T16) | W16: 0.832 | X16: =$G$6*$G$7*W16 | Y16: =W16*($G$9+$G$10) | Z16: 0.07 | AA16: =G16*Z16 | AB16: 0.08 | AC16: =G16*AB16 | AD16: =AA16+AC16 | AE16: =AD16/G16 | AF16: =G16-N16-O16-P16-Q16-R16-S16-V16-X16-Y16-L16-AK16 | AG16: =AF16-AD16 | AH16: =AG16/G16 | AI16: =AG16/L16 | AJ16: =(O16+Q16+V16+X16+Y16+L16)/(1-(M16+$G$4+(1-H16)*$G$3+$G$8+$G$11+Z16+AB16)) | AK16: =G16*$G$11
A17: FARMSTAY - Black Garlic Nourishing Shampoo [530ml] / Шампунь-кондиционер 2в1 с экстрактом черного чеснока | B17: 3360 | C17: 50 | D17: 2156 | E17: 46 | F17: 5 | G17: 1850 | H17: 0.45 | I17: =G17*(1-H17) | J17: 396.72 | K17: =$G$5 | L17: =J17+K17 | M17: 0.41 | N17: =G17*M17 | O17: 75 | P17: =G17*$G$8 | Q17: 25 | R17: =G17*$G$4 | S17: =I17*$G$3 | T17: 0.9 | U17: 75 | V17: =U17*(1-T17) | W17: 1.89 | X17: =$G$6*$G$7*W17 | Y17: =W17*($G$9+$G$10) | Z17: 0.07 | AA17: =G17*Z17 | AB17: 0.08 | AC17: =G17*AB17 | AD17: =AA17+AC17 | AE17: =AD17/G17 | AF17: =G17-N17-O17-P17-Q17-R17-S17-V17-X17-Y17-L17-AK17 | AG17: =AF17-AD17 | AH17: =AG17/G17 | AI17: =AG17/L17 | AJ17: =(O17+Q17+V17+X17+Y17+L17)/(1-(M17+$G$4+(1-H17)*$G$3+$G$8+$G$11+Z17+AB17)) | AK17: =G17*$G$11
A18: FARMSTAY - Escargot Noblesse Intensive Cream [50g] / Крем с муцином королевской улитки | B18: 964 | C18: 50 | D18: 3070 | E18: 48 | F18: 6.6 | G18: 2900 | H18: 0.45 | I18: =G18*(1-H18) | J18: 313.84 | K18: =$G$5 | L18: =J18+K18 | M18: 0.41 | N18: =G18*M18 | O18: 67 | P18: =G18*$G$8 | Q18: 25 | R18: =G18*$G$4 | S18: =I18*$G$3 | T18: 0.9 | U18: 67 | V18: =U18*(1-T18) | W18: 0.86 | X18: =$G$6*$G$7*W18 | Y18: =W18*($G$9+$G$10) | Z18: 0.07 | AA18: =G18*Z18 | AB18: 0.08 | AC18: =G18*AB18 | AD18: =AA18+AC18 | AE18: =AD18/G18 | AF18: =G18-N18-O18-P18-Q18-R18-S18-V18-X18-Y18-L18-AK18 | AG18: =AF18-AD18 | AH18: =AG18/G18 | AI18: =AG18/L18 | AJ18: =(O18+Q18+V18+X18+Y18+L18)/(1-(M18+$G$4+(1-H18)*$G$3+$G$8+$G$11+Z18+AB18)) | AK18: =G18*$G$11
A19: FARMSTAY - Argan Oil Complete Volume Up Shampoo & Conditioner [530ml] / Шампунь-кондиционер с аргановым маслом | B19: 2535 | C19: 50 | D19: 2000 | E19: 23 | F19: 1 | G19: =(1.25*L19+O19+Q19+V19+X19+Y19)/(1-M19-$G$8-$G$4-(1-H19)*$G$3-$G$11-Z19-AB19) | H19: 0.45 | I19: =G19*(1-H19) | J19: 400.76 | K19: =$G$5 | L19: =J19+K19 | M19: 0.41 | N19: =G19*M19 | O19: 75 | P19: =G19*$G$8 | Q19: 25 | R19: =G19*$G$4 | S19: =I19*$G$3 | T19: 0.9 | U19: 75 | V19: =U19*(1-T19) | W19: 1.26 | X19: =$G$6*$G$7*W19 | Y19: =W19*($G$9+$G$10) | Z19: 0.07 | AA19: =G19*Z19 | AB19: 0.08 | AC19: =G19*AB19 | AD19: =AA19+AC19 | AE19: =AD19/G19 | AF19: =G19-N19-O19-P19-Q19-R19-S19-V19-X19-Y19-L19-AK19 | AG19: =AF19-AD19 | AH19: =AG19/G19 | AI19: =AG19/L19 | AJ19: =(O19+Q19+V19+X19+Y19+L19)/(1-(M19+$G$4+(1-H19)*$G$3+$G$8+$G$11+Z19+AB19)) | AK19: =G19*$G$11
A20: FARMSTAY - Collagen Water Full Shampoo & Conditioner [530ml] / Шампунь-кондиционер 2в1 с коллагеном | B20: 3679 | C20: 50 | D20: 2128 | E20: 22 | F20: 7.5 | G20: =(1.25*L20+O20+Q20+V20+X20+Y20)/(1-M20-$G$8-$G$4-(1-H20)*$G$3-$G$11-Z20-AB20) | H20: 0.45 | I20: =G20*(1-H20) | J20: 396.72 | K20: =$G$5 | L20: =J20+K20 | M20: 0.41 | N20: =G20*M20 | O20: 75 | P20: =G20*$G$8 | Q20: 25 | R20: =G20*$G$4 | S20: =I20*$G$3 | T20: 0.9 | U20: 75 | V20: =U20*(1-T20) | W20: 1.26 | X20: =$G$6*$G$7*W20 | Y20: =W20*($G$9+$G$10) | Z20: 0.07 | AA20: =G20*Z20 | AB20: 0.08 | AC20: =G20*AB20 | AD20: =AA20+AC20 | AE20: =AD20/G20 | AF20: =G20-N20-O20-P20-Q20-R20-S20-V20-X20-Y20-L20-AK20 | AG20: =AF20-AD20 | AH20: =AG20/G20 | AI20: =AG20/L20 | AJ20: =(O20+Q20+V20+X20+Y20+L20)/(1-(M20+$G$4+(1-H20)*$G$3+$G$8+$G$11+Z20+AB20)) | AK20: =G20*$G$11
A21: MANYO - Bifida Biome Complex Ampoule [50ml] / Антивозрастная сыворотка для лица | B21: 1473 | C21: 300 | D21: 5800 | E21: 152 | F21: 0 | G21: 5500 | H21: 0.45 | I21: =G21*(1-H21) | J21: 899.78 | K21: =$G$5 | L21: =J21+K21 | M21: 0.41 | N21: =G21*M21 | O21: 63 | P21: =G21*$G$8 | Q21: 25 | R21: =G21*$G$4 | S21: =I21*$G$3 | T21: 0.9 | U21: 63 | V21: =U21*(1-T21) | W21: 0.3 | X21: =$G$6*$G$7*W21 | Y21: =W21*($G$9+$G$10) | Z21: 0.025 | AA21: =G21*Z21 | AB21: 0.025 | AC21: =G21*AB21 | AD21: =AA21+AC21 | AE21: =AD21/G21 | AF21: =G21-N21-O21-P21-Q21-R21-S21-V21-X21-Y21-L21-AK21 | AG21: =AF21-AD21 | AH21: =AG21/G21 | AI21: =AG21/L21 | AJ21: =(O21+Q21+V21+X21+Y21+L21)/(1-(M21+$G$4+(1-H21)*$G$3+$G$8+$G$11+Z21+AB21)) | AK21: =G21*$G$11
A22: MANYO - Galac Whitening Vita Serum [50ml] / Осветляющая сыворотка с Витамином C | B22: 854 | C22: 200 | D22: 4000 | E22: 163 | F22: 0 | G22: 3700 | H22: 0.45 | I22: =G22*(1-H22) | J22: 646.83 | K22: =$G$5 | L22: =J22+K22 | M22: 0.41 | N22: =G22*M22 | O22: 56 | P22: =G22*$G$8 | Q22: 25 | R22: =G22*$G$4 | S22: =I22*$G$3 | T22: 0.9 | U22: 56 | V22: =U22*(1-T22) | W22: 0.19 | X22: =$G$6*$G$7*W22 | Y22: =W22*($G$9+$G$10) | Z22: 0.025 | AA22: =G22*Z22 | AB22: 0.025 | AC22: =G22*AB22 | AD22: =AA22+AC22 | AE22: =AD22/G22 | AF22: =G22-N22-O22-P22-Q22-R22-S22-V22-X22-Y22-L22-AK22 | AG22: =AF22-AD22 | AH22: =AG22/G22 | AI22: =AG22/L22 | AJ22: =(O22+Q22+V22+X22+Y22+L22)/(1-(M22+$G$4+(1-H22)*$G$3+$G$8+$G$11+Z22+AB22)) | AK22: =G22*$G$11
A23: MANYO - Bifida Biome Ampoule Lotion [300ml] / Укрепляющий лосьон с бифидобактериями | B23: 756 | C23: 300 | D23: 4000 | E23: 140 | F23: 0 | G23: 3700 | H23: 0.45 | I23: =G23*(1-H23) | J23: 735.34 | K23: =$G$5 | L23: =J23+K23 | M23: 0.41 | N23: =G23*M23 | O23: 67 | P23: =G23*$G$8 | Q23: 25 | R23: =G23*$G$4 | S23: =I23*$G$3 | T23: 0.9 | U23: 67 | V23: =U23*(1-T23) | W23: 0.61 | X23: =$G$6*$G$7*W23 | Y23: =W23*($G$9+$G$10) | Z23: 0.025 | AA23: =G23*Z23 | AB23: 0.025 | AC23: =G23*AB23 | AD23: =AA23+AC23 | AE23: =AD23/G23 | AF23: =G23-N23-O23-P23-Q23-R23-S23-V23-X23-Y23-L23-AK23 | AG23: =AF23-AD23 | AH23: =AG23/G23 | AI23: =AG23/L23 | AJ23: =(O23+Q23+V23+X23+Y23+L23)/(1-(M23+$G$4+(1-H23)*$G$3+$G$8+$G$11+Z23+AB23)) | AK23: =G23*$G$11
A24: MANYO BIFIDA COMPLEX AMPOULE GEL CLEANSER [400ml] / Гель для умывания с бифидобактериями | B24: 814 | C24: 200 | D24: 4800 | E24: 20 | F24: 0 | G24: 4500 | H24: 0.45 | I24: =G24*(1-H24) | J24: 650 | K24: =$G$5 | L24: =J24+K24 | M24: 0.41 | N24: =G24*M24 | O24: 75 | P24: =G24*$G$8 | Q24: 25 | R24: =G24*$G$4 | S24: =I24*$G$3 | T24: 0.9 | U24: 75 | V24: =U24*(1-T24) | W24: 0.931 | X24: =$G$6*$G$7*W24 | Y24: =W24*($G$9+$G$10) | Z24: 0.025 | AA24: =G24*Z24 | AB24: 0.025 | AC24: =G24*AB24 | AD24: =AA24+AC24 | AE24: =AD24/G24 | AF24: =G24-N24-O24-P24-Q24-R24-S24-V24-X24-Y24-L24-AK24 | AG24: =AF24-AD24 | AH24: =AG24/G24 | AI24: =AG24/L24 | AJ24: =(O24+Q24+V24+X24+Y24+L24)/(1-(M24+$G$4+(1-H24)*$G$3+$G$8+$G$11+Z24+AB24)) | AK24: =G24*$G$11
A25: MANYO BIFIDA INFUSION SHOT AMPOULE 1DX [50ml] / Сыворотка с микроиглами и пробиотиками | B25: 786 | C25: 300 | D25: 3800 | E25: 370 | F25: 0 | G25: 3500 | H25: 0.45 | I25: =G25*(1-H25) | J25: 899.78 | K25: =$G$5 | L25: =J25+K25 | M25: 0.41 | N25: =G25*M25 | O25: 63 | P25: =G25*$G$8 | Q25: 25 | R25: =G25*$G$4 | S25: =I25*$G$3 | T25: 0.9 | U25: 63 | V25: =U25*(1-T25) | W25: 0.3 | X25: =$G$6*$G$7*W25 | Y25: =W25*($G$9+$G$10) | Z25: 0.025 | AA25: =G25*Z25 | AB25: 0.025 | AC25: =G25*AB25 | AD25: =AA25+AC25 | AE25: =AD25/G25 | AF25: =G25-N25-O25-P25-Q25-R25-S25-V25-X25-Y25-L25-AK25 | AG25: =AF25-AD25 | AH25: =AG25/G25 | AI25: =AG25/L25 | AJ25: =(O25+Q25+V25+X25+Y25+L25)/(1-(M25+$G$4+(1-H25)*$G$3+$G$8+$G$11+Z25+AB25)) | AK25: =G25*$G$11
A26: ROUND LAB 1025 DOKDO CLEANSER_150ml | B26: 7158 | C26: 1000 | D26: 2335 | E26: 4000 | F26: 3 | G26: 2200 | H26: 0.45 | I26: =G26*(1-H26) | J26: 463.19 | K26: =$G$5 | L26: =J26+K26 | M26: 0.41 | N26: =G26*M26 | O26: 74 | P26: =G26*$G$8 | Q26: 25 | R26: =G26*$G$4 | S26: =I26*$G$3 | T26: 0.9 | U26: 74 | V26: =U26*(1-T26) | W26: 1.28 | X26: =$G$6*$G$7*W26 | Y26: =W26*($G$9+$G$10) | Z26: 0.07 | AA26: =G26*Z26 | AB26: 0.08 | AC26: =G26*AB26 | AD26: =AA26+AC26 | AE26: =AD26/G26 | AF26: =G26-N26-O26-P26-Q26-R26-S26-V26-X26-Y26-L26-AK26 | AG26: =AF26-AD26 | AH26: =AG26/G26 | AI26: =AG26/L26 | AJ26: =(O26+Q26+V26+X26+Y26+L26)/(1-(M26+$G$4+(1-H26)*$G$3+$G$8+$G$11+Z26+AB26)) | AK26: =G26*$G$11
A27: ROUND LAB 1025 DOKDO TONER_200ml | B27: 998 | C27: 300 | D27: 3400 | E27: 260 | F27: 2 | G27: 3100 | H27: 0.45 | I27: =G27*(1-H27) | J27: 463.19 | K27: =$G$5 | L27: =J27+K27 | M27: 0.41 | N27: =G27*M27 | O27: 74 | P27: =G27*$G$8 | Q27: 25 | R27: =G27*$G$4 | S27: =I27*$G$3 | T27: 0.9 | U27: 74 | V27: =U27*(1-T27) | W27: 1.28 | X27: =$G$6*$G$7*W27 | Y27: =W27*($G$9+$G$10) | Z27: 0.07 | AA27: =G27*Z27 | AB27: 0.08 | AC27: =G27*AB27 | AD27: =AA27+AC27 | AE27: =AD27/G27 | AF27: =G27-N27-O27-P27-Q27-R27-S27-V27-X27-Y27-L27-AK27 | AG27: =AF27-AD27 | AH27: =AG27/G27 | AI27: =AG27/L27 | AJ27: =(O27+Q27+V27+X27+Y27+L27)/(1-(M27+$G$4+(1-H27)*$G$3+$G$8+$G$11+Z27+AB27)) | AK27: =G27*$G$11
A28: Celimax Dual Barrier Creamy Toner | B28: 4929 | C28: 1000 | D28: 2600 | E28: 5500 | F28: 10 | G28: 2450 | H28: 0.45 | I28: =G28*(1-H28) | J28: 663.86 | K28: =$G$5 | L28: =J28+K28 | M28: 0.41 | N28: =G28*M28 | O28: 67 | P28: =G28*$G$8 | Q28: 25 | R28: =G28*$G$4 | S28: =I28*$G$3 | T28: 0.9 | U28: 67 | V28: =U28*(1-T28) | W28: 0.735 | X28: =$G$6*$G$7*W28 | Y28: =W28*($G$9+$G$10) | Z28: 0.05 | AA28: =G28*Z28 | AB28: 0.05 | AC28: =G28*AB28 | AD28: =AA28+AC28 | AE28: =AD28/G28 | AF28: =G28-N28-O28-P28-Q28-R28-S28-V28-X28-Y28-L28-AK28 | AG28: =AF28-AD28 | AH28: =AG28/G28 | AI28: =AG28/L28 | AJ28: =(O28+Q28+V28+X28+Y28+L28)/(1-(M28+$G$4+(1-H28)*$G$3+$G$8+$G$11+Z28+AB28)) | AK28: =G28*$G$11
A29: CELIMAX THE VITA-A RETINAL SHOT TIGHTENING BOOSTER [15ml]/Подтягивающий бустер-крем с ретинолом для лица | B29: 9768 | C29: 1000 | D29: 2250 | E29: 3000 | F29: 13 | G29: 2150 | H29: 0.45 | I29: =G29*(1-H29) | J29: 512.18 | K29: =$G$5 | L29: =J29+K29 | M29: 0.41 | N29: =G29*M29 | O29: 56 | P29: =G29*$G$8 | Q29: 25 | R29: =G29*$G$4 | S29: =I29*$G$3 | T29: 0.9 | U29: 56 | V29: =U29*(1-T29) | W29: 0.18 | X29: =$G$6*$G$7*W29 | Y29: =W29*($G$9+$G$10) | Z29: 0.07 | AA29: =G29*Z29 | AB29: 0.08 | AC29: =G29*AB29 | AD29: =AA29+AC29 | AE29: =AD29/G29 | AF29: =G29-N29-O29-P29-Q29-R29-S29-V29-X29-Y29-L29-AK29 | AG29: =AF29-AD29 | AH29: =AG29/G29 | AI29: =AG29/L29 | AJ29: =(O29+Q29+V29+X29+Y29+L29)/(1-(M29+$G$4+(1-H29)*$G$3+$G$8+$G$11+Z29+AB29)) | AK29: =G29*$G$11
A30: CELIMAX THE VITA-A RETINOL SHOT TIGHTENING SERUM [30ml]/Сыворотка с ретинолом и микроиглами для лица | B30: 3564 | C30: 1000 | D30: 2450 | E30: 3500 | F30: 10 | G30: 2350 | H30: 0.45 | I30: =G30*(1-H30) | J30: 532.1 | K30: =$G$5 | L30: =J30+K30 | M30: 0.41 | N30: =G30*M30 | O30: 63 | P30: =G30*$G$8 | Q30: 25 | R30: =G30*$G$4 | S30: =I30*$G$3 | T30: 0.9 | U30: 63 | V30: =U30*(1-T30) | W30: 0.38 | X30: =$G$6*$G$7*W30 | Y30: =W30*($G$9+$G$10) | Z30: 0.07 | AA30: =G30*Z30 | AB30: 0.08 | AC30: =G30*AB30 | AD30: =AA30+AC30 | AE30: =AD30/G30 | AF30: =G30-N30-O30-P30-Q30-R30-S30-V30-X30-Y30-L30-AK30 | AG30: =AF30-AD30 | AH30: =AG30/G30 | AI30: =AG30/L30 | AJ30: =(O30+Q30+V30+X30+Y30+L30)/(1-(M30+$G$4+(1-H30)*$G$3+$G$8+$G$11+Z30+AB30)) | AK30: =G30*$G$11
A31: CELIMAX JI WOO GAE CICA BHA BLEMISH TONER PAD_10EA [30ml]/успокаивающие тонер-пэды | B31: 1696 | C31: 300 | D31: 775 | E31: 2740 | F31: 11 | G31: 745 | H31: 0.45 | I31: =G31*(1-H31) | J31: 96.94 | K31: =$G$5 | L31: =J31+K31 | M31: 0.41 | N31: =G31*M31 | O31: 56 | P31: =G31*$G$8 | Q31: 25 | R31: =G31*$G$4 | S31: =I31*$G$3 | T31: 0.9 | U31: 56 | V31: =U31*(1-T31) | W31: 0.14 | X31: =$G$6*$G$7*W31 | Y31: =W31*($G$9+$G$10) | Z31: 0.07 | AA31: =G31*Z31 | AB31: 0.08 | AC31: =G31*AB31 | AD31: =AA31+AC31 | AE31: =AD31/G31 | AF31: =G31-N31-O31-P31-Q31-R31-S31-V31-X31-Y31-L31-AK31 | AG31: =AF31-AD31 | AH31: =AG31/G31 | AI31: =AG31/L31 | AJ31: =(O31+Q31+V31+X31+Y31+L31)/(1-(M31+$G$4+(1-H31)*$G$3+$G$8+$G$11+Z31+AB31)) | AK31: =G31*$G$11
A32: CELIMAX JI WOO GAE CICA BHA BLEMISH TONER PAD [170ml / 60pads]/Тонер-пэды от воспалений | B32: 1620 | C32: 300 | D32: 3450 | E32: 1820 | F32: 11 | G32: 3150 | H32: 0.45 | I32: =G32*(1-H32) | J32: 707.88 | K32: =$G$5 | L32: =J32+K32 | M32: 0.41 | N32: =G32*M32 | O32: 67 | P32: =G32*$G$8 | Q32: 25 | R32: =G32*$G$4 | S32: =I32*$G$3 | T32: 0.9 | U32: 67 | V32: =U32*(1-T32) | W32: 0.96 | X32: =$G$6*$G$7*W32 | Y32: =W32*($G$9+$G$10) | Z32: 0.07 | AA32: =G32*Z32 | AB32: 0.08 | AC32: =G32*AB32 | AD32: =AA32+AC32 | AE32: =AD32/G32 | AF32: =G32-N32-O32-P32-Q32-R32-S32-V32-X32-Y32-L32-AK32 | AG32: =AF32-AD32 | AH32: =AG32/G32 | AI32: =AG32/L32 | AJ32: =(O32+Q32+V32+X32+Y32+L32)/(1-(M32+$G$4+(1-H32)*$G$3+$G$8+$G$11+Z32+AB32)) | AK32: =G32*$G$11
... A35: VT REEDLE SHOT 100 / Бустер-сыворотка с микроиглами | B35: 543 | C35: 300 | D35: 5900 | E35: 220 | F35: 11 | G35: 5600 | H35: 0.45 | I35: =G35*(1-H35) | J35: 974.04 | K35: =$G$5 | L35: =J35+K35 | M35: 0.41 | N35: =G35*M35 | O35: 63 | P35: =G35*$G$8 | Q35: 25 | R35: =G35*$G$4 | S35: =I35*$G$3 | T35: 0.9 | U35: 63 | V35: =U35*(1-T35) | W35: 0.4 | X35: =$G$6*$G$7*W35 | Y35: =W35*($G$9+$G$10) | Z35: 0.07 | AA35: =G35*Z35 | AB35: 0.08 | AC35: =G35*AB35 | AD35: =AA35+AC35 | AE35: =AD35/G35 | AF35: =G35-N35-O35-P35-Q35-R35-S35-V35-X35-Y35-L35-AK35 | AG35: =AF35-AD35 | AH35: =AG35/G35 | AI35: =AG35/L35 | AJ35: =(O35+Q35+V35+X35+Y35+L35)/(1-(M35+$G$4+(1-H35)*$G$3+$G$8+$G$11+Z35+AB35)) | AK35: =G35*$G$11

Sheet Раскрутка
A1: Раскрутка на старте: отзывы + самовыкупы (FBO)
A2: Стоимость 1 отзыва, ₽ | B2: 200
A3: Доля самовыкупа от заказов конкурента | B3: 0.3
A4: Прочие расходы на 1 самовыкуп, ₽ (забор с ПВЗ, оформление) | B4: 50
A5: Стартовая доля продаж от конкурента (1-й мес продаж) | B5: 0.3
A6: Ежемесячный рост доли продаж, +п.п. | B6: 0.1
A7: Самовыкуп: платим цену с СПП (покупатель), получаем выплату Ozon с цены продавца (СПП финансирует Ozon), товар возвращается на склад → теряем только сборы Ozon сверх компенсации СПП + прочие расходы. Прибыль по месяцам = доля от конкурента (растёт +10 п.п./мес) × маржа/шт.
A9: Товар | B9: Отзывов, шт | C9: Отзывы, ₽ | D9: Заказы конкур., шт | E9: Самовыкупов, шт | F9: Цена выкупа (с СПП), ₽ | G9: Сборы Ozon / выкуп, ₽ | H9: Компенсация СПП, ₽ | I9: Безвозврат / выкуп, ₽ | J9: Самовыкупы, ₽ | K9: Расходы 1-й мес, ₽ | L9: Маржа/шт, ₽ | M9: Прибыль Сентябрь, ₽ | N9: Прибыль Октябрь, ₽ | O9: Прибыль Ноябрь, ₽ | P9: Прибыль Декабрь, ₽ | Q9: ROI инвестиций (Сен–Дек)
A10: ='Юнитка FBO'!A13 | B10: ='Юнитка FBO'!C13 | C10: =B10*$B$2 | D10: ='Юнитка FBO'!E13 | E10: =ROUND(D10*$B$3,0) | F10: ='Юнитка FBO'!I13 | G10: ='Юнитка FBO'!K13+'Юнитка FBO'!N13+'Юнитка FBO'!O13+'Юнитка FBO'!P13+'Юнитка FBO'!Q13+'Юнитка FBO'!R13+'Юнитка FBO'!S13+'Юнитка FBO'!V13+'Юнитка FBO'!X13+'Юнитка FBO'!Y13+'Юнитка FBO'!AK13 | H10: ='Юнитка FBO'!G13-'Юнитка FBO'!I13 | I10: =MAX(0,G10-H10)+$B$4 | J10: =E10*I10 | K10: =C10+J10 | L10: ='Юнитка FBO'!AG13 | M10: =D10*L10*($B$5+0*$B$6) | N10: =D10*L10*($B$5+1*$B$6) | O10: =D10*L10*($B$5+2*$B$6) | P10: =D10*L10*($B$5+3*$B$6) | Q10: =IF(K10>0,(M10+N10+O10+P10-K10)/K10,"—")
A11: ='Юнитка FBO'!A14 | B11: ='Юнитка FBO'!C14 | C11: =B11*$B$2 | D11: ='Юнитка FBO'!E14 | E11: =ROUND(D11*$B$3,0) | F11: ='Юнитка FBO'!I14 | G11: ='Юнитка FBO'!K14+'Юнитка FBO'!N14+'Юнитка FBO'!O14+'Юнитка FBO'!P14+'Юнитка FBO'!Q14+'Юнитка FBO'!R14+'Юнитка FBO'!S14+'Юнитка FBO'!V14+'Юнитка FBO'!X14+'Юнитка FBO'!Y14+'Юнитка FBO'!AK14 | H11: ='Юнитка FBO'!G14-'Юнитка FBO'!I14 | I11: =MAX(0,G11-H11)+$B$4 | J11: =E11*I11 | K11: =C11+J11 | L11: ='Юнитка FBO'!AG14 | M11: =D11*L11*($B$5+0*$B$6) | N11: =D11*L11*($B$5+1*$B$6) | O11: =D11*L11*($B$5+2*$B$6) | P11: =D11*L11*($B$5+3*$B$6) | Q11: =IF(K11>0,(M11+N11+O11+P11-K11)/K11,"—")
A12: ='Юнитка FBO'!A15 | B12: ='Юнитка FBO'!C15 | C12: =B12*$B$2 | D12: ='Юнитка FBO'!E15 | E12: =ROUND(D12*$B$3,0) | F12: ='Юнитка FBO'!I15 | G12: ='Юнитка FBO'!K15+'Юнитка FBO'!N15+'Юнитка FBO'!O15+'Юнитка FBO'!P15+'Юнитка FBO'!Q15+'Юнитка FBO'!R15+'Юнитка FBO'!S15+'Юнитка FBO'!V15+'Юнитка FBO'!X15+'Юнитка FBO'!Y15+'Юнитка FBO'!AK15 | H12: ='Юнитка FBO'!G15-'Юнитка FBO'!I15 | I12: =MAX(0,G12-H12)+$B$4 | J12: =E12*I12 | K12: =C12+J12 | L12: ='Юнитка FBO'!AG15 | M12: =D12*L12*($B$5+0*$B$6) | N12: =D12*L12*($B$5+1*$B$6) | O12: =D12*L12*($B$5+2*$B$6) | P12: =D12*L12*($B$5+3*$B$6) | Q12: =IF(K12>0,(M12+N12+O12+P12-K12)/K12,"—")
A13: ='Юнитка FBO'!A16 | B13: ='Юнитка FBO'!C16 | C13: =B13*$B$2 | D13: ='Юнитка FBO'!E16 | E13: =ROUND(D13*$B$3,0) | F13: ='Юнитка FBO'!I16 | G13: ='Юнитка FBO'!K16+'Юнитка FBO'!N16+'Юнитка FBO'!O16+'Юнитка FBO'!P16+'Юнитка FBO'!Q16+'Юнитка FBO'!R16+'Юнитка FBO'!S16+'Юнитка FBO'!V16+'Юнитка FBO'!X16+'Юнитка FBO'!Y16+'Юнитка FBO'!AK16 | H13: ='Юнитка FBO'!G16-'Юнитка FBO'!I16 | I13: =MAX(0,G13-H13)+$B$4 | J13: =E13*I13 | K13: =C13+J13 | L13: ='Юнитка FBO'!AG16 | M13: =D13*L13*($B$5+0*$B$6) | N13: =D13*L13*($B$5+1*$B$6) | O13: =D13*L13*($B$5+2*$B$6) | P13: =D13*L13*($B$5+3*$B$6) | Q13: =IF(K13>0,(M13+N13+O13+P13-K13)/K13,"—")
A14: ='Юнитка FBO'!A17 | B14: ='Юнитка FBO'!C17 | C14: =B14*$B$2 | D14: ='Юнитка FBO'!E17 | E14: =ROUND(D14*$B$3,0) | F14: ='Юнитка FBO'!I17 | G14: ='Юнитка FBO'!K17+'Юнитка FBO'!N17+'Юнитка FBO'!O17+'Юнитка FBO'!P17+'Юнитка FBO'!Q17+'Юнитка FBO'!R17+'Юнитка FBO'!S17+'Юнитка FBO'!V17+'Юнитка FBO'!X17+'Юнитка FBO'!Y17+'Юнитка FBO'!AK17 | H14: ='Юнитка FBO'!G17-'Юнитка FBO'!I17 | I14: =MAX(0,G14-H14)+$B$4 | J14: =E14*I14 | K14: =C14+J14 | L14: ='Юнитка FBO'!AG17 | M14: =D14*L14*($B$5+0*$B$6) | N14: =D14*L14*($B$5+1*$B$6) | O14: =D14*L14*($B$5+2*$B$6) | P14: =D14*L14*($B$5+3*$B$6) | Q14: =IF(K14>0,(M14+N14+O14+P14-K14)/K14,"—")
A15: ='Юнитка FBO'!A18 | B15: ='Юнитка FBO'!C18 | C15: =B15*$B$2 | D15: ='Юнитка FBO'!E18 | E15: =ROUND(D15*$B$3,0) | F15: ='Юнитка FBO'!I18 | G15: ='Юнитка FBO'!K18+'Юнитка FBO'!N18+'Юнитка FBO'!O18+'Юнитка FBO'!P18+'Юнитка FBO'!Q18+'Юнитка FBO'!R18+'Юнитка FBO'!S18+'Юнитка FBO'!V18+'Юнитка FBO'!X18+'Юнитка FBO'!Y18+'Юнитка FBO'!AK18 | H15: ='Юнитка FBO'!G18-'Юнитка FBO'!I18 | I15: =MAX(0,G15-H15)+$B$4 | J15: =E15*I15 | K15: =C15+J15 | L15: ='Юнитка FBO'!AG18 | M15: =D15*L15*($B$5+0*$B$6) | N15: =D15*L15*($B$5+1*$B$6) | O15: =D15*L15*($B$5+2*$B$6) | P15: =D15*L15*($B$5+3*$B$6) | Q15: =IF(K15>0,(M15+N15+O15+P15-K15)/K15,"—")
A16: ='Юнитка FBO'!A19 | B16: ='Юнитка FBO'!C19 | C16: =B16*$B$2 | D16: ='Юнитка FBO'!E19 | E16: =ROUND(D16*$B$3,0) | F16: ='Юнитка FBO'!I19 | G16: ='Юнитка FBO'!K19+'Юнитка FBO'!N19+'Юнитка FBO'!O19+'Юнитка FBO'!P19+'Юнитка FBO'!Q19+'Юнитка FBO'!R19+'Юнитка FBO'!S19+'Юнитка FBO'!V19+'Юнитка FBO'!X19+'Юнитка FBO'!Y19+'Юнитка FBO'!AK19 | H16: ='Юнитка FBO'!G19-'Юнитка FBO'!I19 | I16: =MAX(0,G16-H16)+$B$4 | J16: =E16*I16 | K16: =C16+J16 | L16: ='Юнитка FBO'!AG19 | M16: =D16*L16*($B$5+0*$B$6) | N16: =D16*L16*($B$5+1*$B$6) | O16: =D16*L16*($B$5+2*$B$6) | P16: =D16*L16*($B$5+3*$B$6) | Q16: =IF(K16>0,(M16+N16+O16+P16-K16)/K16,"—")
A17: ='Юнитка FBO'!A20 | B17: ='Юнитка FBO'!C20 | C17: =B17*$B$2 | D17: ='Юнитка FBO'!E20 | E17: =ROUND(D17*$B$3,0) | F17: ='Юнитка FBO'!I20 | G17: ='Юнитка FBO'!K20+'Юнитка FBO'!N20+'Юнитка FBO'!O20+'Юнитка FBO'!P20+'Юнитка FBO'!Q20+'Юнитка FBO'!R20+'Юнитка FBO'!S20+'Юнитка FBO'!V20+'Юнитка FBO'!X20+'Юнитка FBO'!Y20+'Юнитка FBO'!AK20 | H17: ='Юнитка FBO'!G20-'Юнитка FBO'!I20 | I17: =MAX(0,G17-H17)+$B$4 | J17: =E17*I17 | K17: =C17+J17 | L17: ='Юнитка FBO'!AG20 | M17: =D17*L17*($B$5+0*$B$6) | N17: =D17*L17*($B$5+1*$B$6) | O17: =D17*L17*($B$5+2*$B$6) | P17: =D17*L17*($B$5+3*$B$6) | Q17: =IF(K17>0,(M17+N17+O17+P17-K17)/K17,"—")
A18: ='Юнитка FBO'!A21 | B18: ='Юнитка FBO'!C21 | C18: =B18*$B$2 | D18: ='Юнитка FBO'!E21 | E18: =ROUND(D18*$B$3,0) | F18: ='Юнитка FBO'!I21 | G18: ='Юнитка FBO'!K21+'Юнитка FBO'!N21+'Юнитка FBO'!O21+'Юнитка FBO'!P21+'Юнитка FBO'!Q21+'Юнитка FBO'!R21+'Юнитка FBO'!S21+'Юнитка FBO'!V21+'Юнитка FBO'!X21+'Юнитка FBO'!Y21+'Юнитка FBO'!AK21 | H18: ='Юнитка FBO'!G21-'Юнитка FBO'!I21 | I18: =MAX(0,G18-H18)+$B$4 | J18: =E18*I18 | K18: =C18+J18 | L18: ='Юнитка FBO'!AG21 | M18: =D18*L18*($B$5+0*$B$6) | N18: =D18*L18*($B$5+1*$B$6) | O18: =D18*L18*($B$5+2*$B$6) | P18: =D18*L18*($B$5+3*$B$6) | Q18: =IF(K18>0,(M18+N18+O18+P18-K18)/K18,"—")
A19: ='Юнитка FBO'!A22 | B19: ='Юнитка FBO'!C22 | C19: =B19*$B$2 | D19: ='Юнитка FBO'!E22 | E19: =ROUND(D19*$B$3,0) | F19: ='Юнитка FBO'!I22 | G19: ='Юнитка FBO'!K22+'Юнитка FBO'!N22+'Юнитка FBO'!O22+'Юнитка FBO'!P22+'Юнитка FBO'!Q22+'Юнитка FBO'!R22+'Юнитка FBO'!S22+'Юнитка FBO'!V22+'Юнитка FBO'!X22+'Юнитка FBO'!Y22+'Юнитка FBO'!AK22 | H19: ='Юнитка FBO'!G22-'Юнитка FBO'!I22 | I19: =MAX(0,G19-H19)+$B$4 | J19: =E19*I19 | K19: =C19+J19 | L19: ='Юнитка FBO'!AG22 | M19: =D19*L19*($B$5+0*$B$6) | N19: =D19*L19*($B$5+1*$B$6) | O19: =D19*L19*($B$5+2*$B$6) | P19: =D19*L19*($B$5+3*$B$6) | Q19: =IF(K19>0,(M19+N19+O19+P19-K19)/K19,"—")
A20: ='Юнитка FBO'!A23 | B20: ='Юнитка FBO'!C23 | C20: =B20*$B$2 | D20: ='Юнитка FBO'!E23 | E20: =ROUND(D20*$B$3,0) | F20: ='Юнитка FBO'!I23 | G20: ='Юнитка FBO'!K23+'Юнитка FBO'!N23+'Юнитка FBO'!O23+'Юнитка FBO'!P23+'Юнитка FBO'!Q23+'Юнитка FBO'!R23+'Юнитка FBO'!S23+'Юнитка FBO'!V23+'Юнитка FBO'!X23+'Юнитка FBO'!Y23+'Юнитка FBO'!AK23 | H20: ='Юнитка FBO'!G23-'Юнитка FBO'!I23 | I20: =MAX(0,G20-H20)+$B$4 | J20: =E20*I20 | K20: =C20+J20 | L20: ='Юнитка FBO'!AG23 | M20: =D20*L20*($B$5+0*$B$6) | N20: =D20*L20*($B$5+1*$B$6) | O20: =D20*L20*($B$5+2*$B$6) | P20: =D20*L20*($B$5+3*$B$6) | Q20: =IF(K20>0,(M20+N20+O20+P20-K20)/K20,"—")
A21: ='Юнитка FBO'!A24 | B21: ='Юнитка FBO'!C24 | C21: =B21*$B$2 | D21: ='Юнитка FBO'!E24 | E21: =ROUND(D21*$B$3,0) | F21: ='Юнитка FBO'!I24 | G21: ='Юнитка FBO'!K24+'Юнитка FBO'!N24+'Юнитка FBO'!O24+'Юнитка FBO'!P24+'Юнитка FBO'!Q24+'Юнитка FBO'!R24+'Юнитка FBO'!S24+'Юнитка FBO'!V24+'Юнитка FBO'!X24+'Юнитка FBO'!Y24+'Юнитка FBO'!AK24 | H21: ='Юнитка FBO'!G24-'Юнитка FBO'!I24 | I21: =MAX(0,G21-H21)+$B$4 | J21: =E21*I21 | K21: =C21+J21 | L21: ='Юнитка FBO'!AG24 | M21: =D21*L21*($B$5+0*$B$6) | N21: =D21*L21*($B$5+1*$B$6) | O21: =D21*L21*($B$5+2*$B$6) | P21: =D21*L21*($B$5+3*$B$6) | Q21: =IF(K21>0,(M21+N21+O21+P21-K21)/K21,"—")
... A32: ='Юнитка FBO'!A35 | B32: ='Юнитка FBO'!C35 | C32: =B32*$B$2 | D32: ='Юнитка FBO'!E35 | E32: =ROUND(D32*$B$3,0) | F32: ='Юнитка FBO'!I35 | G32: ='Юнитка FBO'!K35+'Юнитка FBO'!N35+'Юнитка FBO'!O35+'Юнитка FBO'!P35+'Юнитка FBO'!Q35+'Юнитка FBO'!R35+'Юнитка FBO'!S35+'Юнитка FBO'!V35+'Юнитка FBO'!X35+'Юнитка FBO'!Y35+'Юнитка FBO'!AK35 | H32: ='Юнитка FBO'!G35-'Юнитка FBO'!I35 | I32: =MAX(0,G32-H32)+$B$4 | J32: =E32*I32 | K32: =C32+J32 | L32: ='Юнитка FBO'!AG35 | M32: =D32*L32*($B$5+0*$B$6) | N32: =D32*L32*($B$5+1*$B$6) | O32: =D32*L32*($B$5+2*$B$6) | P32: =D32*L32*($B$5+3*$B$6) | Q32: =IF(K32>0,(M32+N32+O32+P32-K32)/K32,"—")
A33: ИТОГО | B33: =SUM(B10:B32) | C33: =SUM(C10:C32) | D33: =SUM(D10:D32) | E33: =SUM(E10:E32) | J33: =SUM(J10:J32) | K33: =SUM(K10:K32) | M33: =SUM(M10:M32) | N33: =SUM(N10:N32) | O33: =SUM(O10:O32) | P33: =SUM(P10:P32) | Q33: =IF(K33>0,(M33+N33+O33+P33-K33)/K33,"—")
A36: План по месяцам: раскрутка + выход на продажи (доля от конкурента растёт на +10 п.п./мес)
A37: Месяц | B37: Доля от продаж конкурента | C37: Продаж, шт | D37: Прибыль от продаж, ₽ | E37: Расходы (накрутка), ₽ | F37: Чистый поток, ₽ | G37: Накопительно, ₽
A38: Август (раскрутка) | B38: 0 | C38: 0 | D38: 0 | E38: =$K$33 | F38: =D38-E38 | G38: =F38
A39: Сентябрь | B39: =$B$5+0*$B$6 | C39: =ROUND(B39*$D$33,0) | D39: =M33 | E39: 0 | F39: =D39-E39 | G39: =G38+F39
A40: Октябрь | B40: =$B$5+1*$B$6 | C40: =ROUND(B40*$D$33,0) | D40: =N33 | E40: 0 | F40: =D40-E40 | G40: =G39+F40
A41: Ноябрь | B41: =$B$5+2*$B$6 | C41: =ROUND(B41*$D$33,0) | D41: =O33 | E41: 0 | F41: =D41-E41 | G41: =G40+F41
A42: Декабрь | B42: =$B$5+3*$B$6 | C42: =ROUND(B42*$D$33,0) | D42: =P33 | E42: 0 | F42: =D42-E42 | G42: =G41+F42
A43: Итого за период | C43: =SUM(C38:C42) | D43: =SUM(D38:D42) | E43: =SUM(E38:E42) | F43: =SUM(F38:F42) | G43: =G42
A45: Разовые расходы на раскрутку (август), ₽ | B45: =$K$33
A46: Прибыль при 100% продаж конкурента, ₽/мес | B46: =SUMPRODUCT(D10:D32,L10:L32)
A47: Накопительный поток к декабрю, ₽ | B47: =G42
A48: Окупаемость раскрутки, мес продаж (при 100%) | B48: =IF(SUMPRODUCT(D10:D32,L10:L32)>0,$K$33/SUMPRODUCT(D10:D32,L10:L32),"—")
