Workbook

Sheet Параметры
A1: Отгрузка ИП Петров Е.А. от 20.08.2026
A2: ТОРГ-12 № 00142, 47 позиций, 6 047 шт
A4: Изменяемые параметры
A5: Курс KRW/RUB, ₽ за 1000 вон | B5: 58.2 | C5: ЦБ РФ на 20.08.2026
A6: Коэффициент доставки до Москвы | B6: 1.3 | C6: 30% сверху к цене закупа в Корее
A8: Учётная себестоимость (последний приход)
A9: Себестоимость, ₽ | B9: ='По брендам'!E12 -> 2472660.4
A10: Прибыль, ₽ | B10: ='По брендам'!F12 -> 246502.64
A11: Наценка | B11: ='По брендам'!G12 -> 0.099691265
A13: Если закупить сегодня в Корее
A14: Закуп, вон | B14: ='По брендам'!L12 -> 33413270
A15: Закуп, ₽ | B15: =B14*B5/1000 -> 1944652.3
A16: Доставка 30%, ₽ | B16: =B15*(B6-1) -> 583395.69
A17: Итого в Москве, ₽ | B17: =B15*B6 -> 2528048
A18: Прибыль, ₽ | B18: ='По брендам'!D12-B17 -> 191114.99
A19: Наценка | B19: =B18/B17 -> 0.075597849
A21: Разница | B21: =B18-B10 -> -55387.648 | C21: насколько прибыль ниже учётной

Sheet Маржа по позициям
A1: № | B1: Бренд | C1: Наименование | D1: Кол-во | E1: Цена продажи, ₽ | F1: Себестоимость, ₽ | G1: Наценка, % | H1: Прибыль на ед., ₽ | I1: Прибыль всего, ₽ | J1: Выручка, ₽ | K1: Закуп, вон | L1: Источник себест. | M1: Закуп, вон/шт | N1: Закуп всего, вон | O1: Закуп сегодня, ₽ | P1: Итого в Москве, ₽ | Q1: Себест. сегодня за ед., ₽ | R1: Маржа к сегодняшней закупке | S1: Источник цены закупа
A2: 1 | B2: ENOUGH | C2: ENOUGH - Collagen Moisture Essential Cream [50ml] | D2: 400 | E2: 177 | F2: 161.3 | G2: =(E2-F2)/F2 -> 0.09733416 | H2: =E2-F2 -> 15.7 | I2: =D2*H2 -> 6280 | J2: =D2*E2 -> 70800 | K2: 2100 | L2: артикул | M2: 2100 | N2: =D2*M2 -> 840000 | O2: =N2*Параметры!$B$5/1000 -> 48888 | P2: =O2*Параметры!$B$6 -> 63554.4 | Q2: =P2/D2 -> 158.886 | R2: =(J2-P2)/P2 -> 0.11400627 | S2: прайс
A3: 2 | B3: ENOUGH | C3: ENOUGH - Collagen Whitening Moisture Cream 3in1 [50g] | D3: 200 | E3: 202 | F3: 183.88 | G3: =(E3-F3)/F3 -> 0.098542528 | H3: =E3-F3 -> 18.12 | I3: =D3*H3 -> 3624 | J3: =D3*E3 -> 40400 | K3: 2500 | L3: артикул | M3: 2500 | N3: =D3*M3 -> 500000 | O3: =N3*Параметры!$B$5/1000 -> 29100 | P3: =O3*Параметры!$B$6 -> 37830 | Q3: =P3/D3 -> 189.15 | R3: =(J3-P3)/P3 -> 0.067935501 | S3: прайс
A4: 3 | B4: ENOUGH | C4: ENOUGH - Collagen Moisture Foundation [Tone 13] | D4: 300 | E4: 238 | F4: 216.45 | G4: =(E4-F4)/F4 -> 0.0995611 | H4: =E4-F4 -> 21.55 | I4: =D4*H4 -> 6465 | J4: =D4*E4 -> 71400 | K4: 2700 | L4: артикул | M4: 2700 | N4: =D4*M4 -> 810000 | O4: =N4*Параметры!$B$5/1000 -> 47142 | P4: =O4*Параметры!$B$6 -> 61284.6 | Q4: =P4/D4 -> 204.282 | R4: =(J4-P4)/P4 -> 0.16505615 | S4: прайс
A5: 4 | B5: ENOUGH | C5: ENOUGH - Collagen Moisture Foundation [Tone 21] | D5: 200 | E5: 267 | F5: 242.88 | G5: =(E5-F5)/F5 -> 0.0993083 | H5: =E5-F5 -> 24.12 | I5: =D5*H5 -> 4824 | J5: =D5*E5 -> 53400 | K5: 2700 | L5: артикул | M5: 2700 | N5: =D5*M5 -> 540000 | O5: =N5*Параметры!$B$5/1000 -> 31428 | P5: =O5*Параметры!$B$6 -> 40856.4 | Q5: =P5/D5 -> 204.282 | R5: =(J5-P5)/P5 -> 0.30701677 | S5: прайс
A6: 5 | B6: ENOUGH | C6: ENOUGH - Collagen 3in1 Whitening Moisture Foundation [Tone 13] | D6: 100 | E6: 262 | F6: 238.13 | G6: =(E6-F6)/F6 -> 0.10023937 | H6: =E6-F6 -> 23.87 | I6: =D6*H6 -> 2387 | J6: =D6*E6 -> 26200 | K6: 2992 | L6: артикул | M6: 2992 | N6: =D6*M6 -> 299200 | O6: =N6*Параметры!$B$5/1000 -> 17413.44 | P6: =O6*Параметры!$B$6 -> 22637.472 | Q6: =P6/D6 -> 226.37472 | R6: =(J6-P6)/P6 -> 0.15737305 | S6: прайс
A7: 6 | B7: ENOUGH | C7: ENOUGH - Premium 8 Peptide Full Cover Perfect Foundation [Tone 13] | D7: 200 | E7: 369 | F7: 335.9 | G7: =(E7-F7)/F7 -> 0.098541233 | H7: =E7-F7 -> 33.1 | I7: =D7*H7 -> 6620 | J7: =D7*E7 -> 73800 | K7: 3850 | L7: артикул | M7: 3850 | N7: =D7*M7 -> 770000 | O7: =N7*Параметры!$B$5/1000 -> 44814 | P7: =O7*Параметры!$B$6 -> 58258.2 | Q7: =P7/D7 -> 291.291 | R7: =(J7-P7)/P7 -> 0.26677446 | S7: прайс
A8: 7 | B8: ETUDE | C8: ETUDE - Baking Powder Crunch Pore Scrub [200ml] | D8: 360 | E8: 397 | F8: 361.03 | G8: =(E8-F8)/F8 -> 0.09963161 | H8: =E8-F8 -> 35.97 | I8: =D8*H8 -> 12949.2 | J8: =D8*E8 -> 142920 | K8: 4500 | L8: артикул | M8: 4500 | N8: =D8*M8 -> 1620000 | O8: =N8*Параметры!$B$5/1000 -> 94284 | P8: =O8*Параметры!$B$6 -> 122569.2 | Q8: =P8/D8 -> 340.47 | R8: =(J8-P8)/P8 -> 0.16603519 | S8: прайс
A9: 8 | B9: ETUDE | C9: ETUDE - Baking Powder Crunch Pore Scrub [24*7ml] | D9: 192 | E9: 429 | F9: 389.99 | G9: =(E9-F9)/F9 -> 0.10002821 | H9: =E9-F9 -> 39.01 | I9: =D9*H9 -> 7489.92 | J9: =D9*E9 -> 82368 | K9: 4900 | L9: артикул | M9: 4900 | N9: =D9*M9 -> 940800 | O9: =N9*Параметры!$B$5/1000 -> 54754.56 | P9: =O9*Параметры!$B$6 -> 71180.928 | Q9: =P9/D9 -> 370.734 | R9: =(J9-P9)/P9 -> 0.1571639 | S9: прайс
A10: 9 | B10: FARMSTAY | C10: FARMSTAY - Collagen Pure Cleansing Foam [180ml] | D10: 100 | E10: 178 | F10: 161.47 | G10: =(E10-F10)/F10 -> 0.10237196 | H10: =E10-F10 -> 16.53 | I10: =D10*H10 -> 1653 | J10: =D10*E10 -> 17800 | K10: 1795 | L10: артикул | M10: 1795 | N10: =D10*M10 -> 179500 | O10: =N10*Параметры!$B$5/1000 -> 10446.9 | P10: =O10*Параметры!$B$6 -> 13580.97 | Q10: =P10/D10 -> 135.8097 | R10: =(J10-P10)/P10 -> 0.31065749 | S10: прайс
A11: 10 | B11: JMSOLUTION | C11: JMSOLUTION - ACTIVE BLACK CAVIAR Mask [30ml*10ea] | D11: 40 | E11: 376 | F11: 342.27 | G11: =(E11-F11)/F11 -> 0.09854793 | H11: =E11-F11 -> 33.73 | I11: =D11*H11 -> 1349.2 | J11: =D11*E11 -> 15040 | L11: название 100% | M11: 3300 | N11: =D11*M11 -> 132000 | O11: =N11*Параметры!$B$5/1000 -> 7682.4 | P11: =O11*Параметры!$B$6 -> 9987.12 | Q11: =P11/D11 -> 249.678 | R11: =(J11-P11)/P11 -> 0.50593965 | S11: аналог
A12: 11 | B12: JMSOLUTION | C12: JMSOLUTION - Active Golden Caviar Nourishing Mask [30ml*10ea] | D12: 40 | E12: 376 | F12: 342.27 | G12: =(E12-F12)/F12 -> 0.09854793 | H12: =E12-F12 -> 33.73 | I12: =D12*H12 -> 1349.2 | J12: =D12*E12 -> 15040 | K12: 3300 | L12: название 100% | M12: 3300 | N12: =D12*M12 -> 132000 | O12: =N12*Параметры!$B$5/1000 -> 7682.4 | P12: =O12*Параметры!$B$6 -> 9987.12 | Q12: =P12/D12 -> 249.678 | R12: =(J12-P12)/P12 -> 0.50593965 | S12: прайс
A13: 12 | B13: JMSOLUTION | C13: JMSOLUTION - Active Jellyfish Vital Mask [30ml*10ea] | D13: 40 | E13: 376 | F13: 342.27 | G13: =(E13-F13)/F13 -> 0.09854793 | H13: =E13-F13 -> 33.73 | I13: =D13*H13 -> 1349.2 | J13: =D13*E13 -> 15040 | K13: 3300 | L13: название 100% | M13: 3300 | N13: =D13*M13 -> 132000 | O13: =N13*Параметры!$B$5/1000 -> 7682.4 | P13: =O13*Параметры!$B$6 -> 9987.12 | Q13: =P13/D13 -> 249.678 | R13: =(J13-P13)/P13 -> 0.50593965 | S13: прайс
A14: 13 | B14: JMSOLUTION | C14: JMSOLUTION - Active Birds Nest Moisture Mask [30ml*10ea] | D14: 40 | E14: 376 | F14: 342.27 | G14: =(E14-F14)/F14 -> 0.09854793 | H14: =E14-F14 -> 33.73 | I14: =D14*H14 -> 1349.2 | J14: =D14*E14 -> 15040 | K14: 3300 | L14: название 100% | M14: 3300 | N14: =D14*M14 -> 132000 | O14: =N14*Параметры!$B$5/1000 -> 7682.4 | P14: =O14*Параметры!$B$6 -> 9987.12 | Q14: =P14/D14 -> 249.678 | R14: =(J14-P14)/P14 -> 0.50593965 | S14: прайс
A15: 14 | B15: JMSOLUTION | C15: JMSOLUTION GLORY AQUA FULLERENE MASK DELUXE [30ml*10ea] | D15: 40 | E15: 495 | F15: 450.35 | G15: =(E15-F15)/F15 -> 0.099145109 | H15: =E15-F15 -> 44.65 | I15: =D15*H15 -> 1786 | J15: =D15*E15 -> 19800 | L15: название 75% | M15: 4910 | N15: =D15*M15 -> 196400 | O15: =N15*Параметры!$B$5/1000 -> 11430.48 | P15: =O15*Параметры!$B$6 -> 14859.624 | Q15: =P15/D15 -> 371.4906 | R15: =(J15-P15)/P15 -> 0.33246979 | S15: аналог
A16: 15 | B16: JMSOLUTION | C16: JMSOLUTION - Glory Aqua TOCOPHEROL VITAMIN C MASK PLUS [30ml*10ea] | D16: 40 | E16: 495 | F16: 450 | G16: =(E16-F16)/F16 -> 0.1 | H16: =E16-F16 -> 45 | I16: =D16*H16 -> 1800 | J16: =D16*E16 -> 19800 | L16: указана вручную | M16: 4910 | N16: =D16*M16 -> 196400 | O16: =N16*Параметры!$B$5/1000 -> 11430.48 | P16: =O16*Параметры!$B$6 -> 14859.624 | Q16: =P16/D16 -> 371.4906 | R16: =(J16-P16)/P16 -> 0.33246979 | S16: аналог
A17: 16 | B17: JMSOLUTION | C17: JMSOLUTION - Panthelene Intensive Barrier Mask [30ml*10ea] | D17: 40 | E17: 495 | F17: 450.35 | G17: =(E17-F17)/F17 -> 0.099145109 | H17: =E17-F17 -> 44.65 | I17: =D17*H17 -> 1786 | J17: =D17*E17 -> 19800 | L17: название 71% | M17: 4910 | N17: =D17*M17 -> 196400 | O17: =N17*Параметры!$B$5/1000 -> 11430.48 | P17: =O17*Параметры!$B$6 -> 14859.624 | Q17: =P17/D17 -> 371.4906 | R17: =(J17-P17)/P17 -> 0.33246979 | S17: аналог
A18: 17 | B18: JMSOLUTION | C18: JMSOLUTION - The Natural Cordyceps Melitaris Mask Moisture [30ml*10ea] | D18: 40 | E18: 350 | F18: 318.45 | G18: =(E18-F18)/F18 -> 0.099073638 | H18: =E18-F18 -> 31.55 | I18: =D18*H18 -> 1262 | J18: =D18*E18 -> 14000 | L18: название 100% | M18: 3300 | N18: =D18*M18 -> 132000 | O18: =N18*Параметры!$B$5/1000 -> 7682.4 | P18: =O18*Параметры!$B$6 -> 9987.12 | Q18: =P18/D18 -> 249.678 | R18: =(J18-P18)/P18 -> 0.40180553 | S18: аналог
A19: 18 | B19: JMSOLUTION | C19: JMSOLUTION - Water Luminous S.O.S. Ringer AMINO MASK PLUS Black [35ml*10ea] | D19: 40 | E19: 495 | F19: 450.35 | G19: =(E19-F19)/F19 -> 0.099145109 | H19: =E19-F19 -> 44.65 | I19: =D19*H19 -> 1786 | J19: =D19*E19 -> 19800 | K19: 4910 | L19: название 80% | M19: 4910 | N19: =D19*M19 -> 196400 | O19: =N19*Параметры!$B$5/1000 -> 11430.48 | P19: =O19*Параметры!$B$6 -> 14859.624 | Q19: =P19/D19 -> 371.4906 | R19: =(J19-P19)/P19 -> 0.33246979 | S19: прайс
A20: 19 | B20: JMSOLUTION | C20: JMSOLUTION - Green Dear Tiger Cica Mask [30ml*10ea] | D20: 40 | E20: 376 | F20: 342.27 | G20: =(E20-F20)/F20 -> 0.09854793 | H20: =E20-F20 -> 33.73 | I20: =D20*H20 -> 1349.2 | J20: =D20*E20 -> 15040 | K20: 3300 | L20: название 89% | M20: 3300 | N20: =D20*M20 -> 132000 | O20: =N20*Параметры!$B$5/1000 -> 7682.4 | P20: =O20*Параметры!$B$6 -> 9987.12 | Q20: =P20/D20 -> 249.678 | R20: =(J20-P20)/P20 -> 0.50593965 | S20: прайс
A21: 20 | B21: MANYO | C21: MANYO - Bifida Biome Complex Ampoule [50ml] | D21: 70 | E21: 990 | F21: 899.78 | G21: =(E21-F21)/F21 -> 0.10026895 | H21: =E21-F21 -> 90.22 | I21: =D21*H21 -> 6315.4 | J21: =D21*E21 -> 69300 | K21: 14350 | L21: артикул | M21: 14350 | N21: =D21*M21 -> 1004500 | O21: =N21*Параметры!$B$5/1000 -> 58461.9 | P21: =O21*Параметры!$B$6 -> 76000.47 | Q21: =P21/D21 -> 1085.721 | R21: =(J21-P21)/P21 -> -0.088163534 | S21: прайс
A22: 21 | B22: MANYO | C22: MANYO - Galac Whitening Vita Serum [50ml] | D22: 70 | E22: 712 | F22: 646.83 | G22: =(E22-F22)/F22 -> 0.1007529 | H22: =E22-F22 -> 65.17 | I22: =D22*H22 -> 4561.9 | J22: =D22*E22 -> 49840 | K22: 10250 | L22: артикул | M22: 10250 | N22: =D22*M22 -> 717500 | O22: =N22*Параметры!$B$5/1000 -> 41758.5 | P22: =O22*Параметры!$B$6 -> 54286.05 | Q22: =P22/D22 -> 775.515 | R22: =(J22-P22)/P22 -> -0.081900415 | S22: прайс
A23: 22 | B23: MANYO | C23: MANYO - Bifida Biome Ampoule Lotion [300ml] | D23: 120 | E23: 809 | F23: 735.34 | G23: =(E23-F23)/F23 -> 0.10017135 | H23: =E23-F23 -> 73.66 | I23: =D23*H23 -> 8839.2 | J23: =D23*E23 -> 97080 | K23: 10250 | L23: артикул | M23: 10250 | N23: =D23*M23 -> 1230000 | O23: =N23*Параметры!$B$5/1000 -> 71586 | P23: =O23*Параметры!$B$6 -> 93061.8 | Q23: =P23/D23 -> 775.515 | R23: =(J23-P23)/P23 -> 0.043177759 | S23: прайс
A24: 23 | B24: MANYO | C24: MANYO BIFIDA COMPLEX AMPOULE GEL CLEANSER [400ml] | D24: 140 | E24: 814 | F24: 739.91 | G24: =(E24-F24)/F24 -> 0.1001338 | H24: =E24-F24 -> 74.09 | I24: =D24*H24 -> 10372.6 | J24: =D24*E24 -> 113960 | K24: 9200 | L24: артикул | M24: 9200 | N24: =D24*M24 -> 1288000 | O24: =N24*Параметры!$B$5/1000 -> 74961.6 | P24: =O24*Параметры!$B$6 -> 97450.08 | Q24: =P24/D24 -> 696.072 | R24: =(J24-P24)/P24 -> 0.16941926 | S24: прайс
A25: 24 | B25: MANYO | C25: MANYO BIFIDA INFUSION SHOT AMPOULE 1DX [50ml] | D25: 140 | E25: 1096 | F25: 996.75 | G25: =(E25-F25)/F25 -> 0.099573614 | H25: =E25-F25 -> 99.25 | I25: =D25*H25 -> 13895 | J25: =D25*E25 -> 153440 | K25: 16000 | L25: артикул | M25: 16000 | N25: =D25*M25 -> 2240000 | O25: =N25*Параметры!$B$5/1000 -> 130368 | P25: =O25*Параметры!$B$6 -> 169478.4 | Q25: =P25/D25 -> 1210.56 | R25: =(J25-P25)/P25 -> -0.094633888 | S25: прайс
A26: 25 | B26: PETITFEE | C26: PETITFEE - Collagen & CoQ10 Hydrogel Eye Patch [60ea] | D26: 216 | E26: 424 | F26: 385.05 | G26: =(E26-F26)/F26 -> 0.10115569 | H26: =E26-F26 -> 38.95 | I26: =D26*H26 -> 8413.2 | J26: =D26*E26 -> 91584 | K26: 5370 | L26: артикул | M26: 5370 | N26: =D26*M26 -> 1159920 | O26: =N26*Параметры!$B$5/1000 -> 67507.344 | P26: =O26*Параметры!$B$6 -> 87759.547 | Q26: =P26/D26 -> 406.2942 | R26: =(J26-P26)/P26 -> 0.043578766 | S26: прайс
A27: 26 | B27: PETITFEE | C27: PETITFEE - Bera Glucan Deep Firming Eye Patch [60ea] | D27: 60 | E27: 532 | F27: 486.69 | G27: =(E27-F27)/F27 -> 0.093098276 | H27: =E27-F27 -> 45.31 | I27: =D27*H27 -> 2718.6 | J27: =D27*E27 -> 31920 | K27: 6760 | L27: артикул | M27: 6760 | N27: =D27*M27 -> 405600 | O27: =N27*Параметры!$B$5/1000 -> 23605.92 | P27: =O27*Параметры!$B$6 -> 30687.696 | Q27: =P27/D27 -> 511.4616 | R27: =(J27-P27)/P27 -> 0.040156289 | S27: прайс
A28: 27 | B28: PETITFEE | C28: PETITFEE - Artichoke Soothing Hydrogel Eye Patch [60ea] | D28: 144 | E28: 457 | F28: 415.46 | G28: =(E28-F28)/F28 -> 0.099985558 | H28: =E28-F28 -> 41.54 | I28: =D28*H28 -> 5981.76 | J28: =D28*E28 -> 65808 | K28: 5790 | L28: артикул | M28: 5790 | N28: =D28*M28 -> 833760 | O28: =N28*Параметры!$B$5/1000 -> 48524.832 | P28: =O28*Параметры!$B$6 -> 63082.282 | Q28: =P28/D28 -> 438.0714 | R28: =(J28-P28)/P28 -> 0.043208938 | S28: прайс
A29: 28 | B29: PETITFEE | C29: PETITFEE - Cacao Energizing Hydrogel Eye Patch [60ea] | D29: 216 | E29: 457 | F29: 415.46 | G29: =(E29-F29)/F29 -> 0.099985558 | H29: =E29-F29 -> 41.54 | I29: =D29*H29 -> 8972.64 | J29: =D29*E29 -> 98712 | K29: 5790 | L29: артикул | M29: 5790 | N29: =D29*M29 -> 1250640 | O29: =N29*Параметры!$B$5/1000 -> 72787.248 | P29: =O29*Параметры!$B$6 -> 94623.422 | Q29: =P29/D29 -> 438.0714 | R29: =(J29-P29)/P29 -> 0.043208938 | S29: прайс
A30: 29 | B30: PETITFEE | C30: PETITFEE - Chamomile Lightening Hydrogel Eye Patch [60ea] | D30: 143 | E30: 457 | F30: 415.46 | G30: =(E30-F30)/F30 -> 0.099985558 | H30: =E30-F30 -> 41.54 | I30: =D30*H30 -> 5940.22 | J30: =D30*E30 -> 65351 | K30: 5790 | L30: артикул | M30: 5790 | N30: =D30*M30 -> 827970 | O30: =N30*Параметры!$B$5/1000 -> 48187.854 | P30: =O30*Параметры!$B$6 -> 62644.21 | Q30: =P30/D30 -> 438.0714 | R30: =(J30-P30)/P30 -> 0.043208938 | S30: прайс
... A48: 47 | B48: MANYO | C48: MANYO - Pure Cleansing Oil [200ml] | D48: 80 | E48: 938 | F48: 853 | G48: =(E48-F48)/F48 -> 0.0996483 | H48: =E48-F48 -> 85 | I48: =D48*H48 -> 6800 | J48: =D48*E48 -> 75040 | K48: 11920 | L48: артикул | M48: 11920 | N48: =D48*M48 -> 953600 | O48: =N48*Параметры!$B$5/1000 -> 55499.52 | P48: =O48*Параметры!$B$6 -> 72149.376 | Q48: =P48/D48 -> 901.8672 | R48: =(J48-P48)/P48 -> 0.040064435 | S48: прайс
C49: ИТОГО | D49: =SUM(D2:D48) -> 6047 | G49: =I49/(J49-I49) -> 0.099691265 | I49: =SUM(I2:I48) -> 246502.64 | J49: =SUM(J2:J48) -> 2719163 | N49: =SUM(N2:N48) -> 33413270 | O49: =SUM(O2:O48) -> 1944652.3 | P49: =SUM(P2:P48) -> 2528048 | Q49: =P49/D49 -> 418.06648 | R49: =(J49-P49)/P49 -> 0.075597849

Sheet По брендам
A1: Бренд | B1: Позиций | C1: Кол-во, шт | D1: Выручка, ₽ | E1: Себест. учётная, ₽ | F1: Прибыль учётная, ₽ | G1: Наценка учётная | H1: Доля выручки | I1: Доля прибыли | J1: Доля по штукам | K1: Средняя цена, ₽ | L1: Закуп, вон | M1: Итого в Москве сегодня, ₽ | N1: Прибыль сегодня, ₽ | O1: Наценка сегодня | P1: Доля закупки
A2: PETITFEE | B2: 17 | C2: 2135 | D2: 998555 | E2: 907939.78 | F2: =D2-E2 -> 90615.22 | G2: =F2/E2 -> 0.099803117 | H2: =D2/$D$12 -> 0.36722881 | I2: =F2/$F$12 -> 0.36760345 | J2: =C2/$C$12 -> 0.35306764 | K2: =D2/C2 -> 467.70726 | L2: 12561570 | M2: =L2*Параметры!$B$5/1000*Параметры!$B$6 -> 950408.39 | N2: =D2-M2 -> 48146.614 | O2: =N2/M2 -> 0.050658869 | P2: =M2/$M$12 -> 0.37594554
A3: MANYO | B3: 6 | C3: 620 | D3: 558660 | E3: 507875.9 | F3: =D3-E3 -> 50784.1 | G3: =F3/E3 -> 0.099993128 | H3: =D3/$D$12 -> 0.20545293 | I3: =F3/$F$12 -> 0.20601848 | J3: =C3/$C$12 -> 0.10253018 | K3: =D3/C3 -> 901.06452 | L3: 7433600 | M3: =L3*Параметры!$B$5/1000*Параметры!$B$6 -> 562426.18 | N3: =D3-M3 -> -3766.176 | O3: =N3/M3 -> -0.0066963028 | P3: =M3/$M$12 -> 0.22247448
A4: ENOUGH | B4: 6 | C4: 1400 | D4: 336000 | E4: 305800 | F4: =D4-E4 -> 30200 | G4: =F4/E4 -> 0.098757358 | H4: =D4/$D$12 -> 0.12356744 | I4: =F4/$F$12 -> 0.1225139 | J4: =C4/$C$12 -> 0.23151976 | K4: =D4/C4 -> 240 | L4: 3759200 | M4: =L4*Параметры!$B$5/1000*Параметры!$B$6 -> 284421.07 | N4: =D4-M4 -> 51578.928 | O4: =N4/M4 -> 0.18134707 | P4: =M4/$M$12 -> 0.1125062
A5: ETUDE | B5: 2 | C5: 552 | D5: 225288 | E5: 204848.88 | F5: =D5-E5 -> 20439.12 | G5: =F5/E5 -> 0.099776577 | H5: =D5/$D$12 -> 0.082851966 | I5: =F5/$F$12 -> 0.082916434 | J5: =C5/$C$12 -> 0.091284935 | K5: =D5/C5 -> 408.13043 | L5: 2560800 | M5: =L5*Параметры!$B$5/1000*Параметры!$B$6 -> 193750.13 | N5: =D5-M5 -> 31537.872 | O5: =N5/M5 -> 0.16277601 | P5: =M5/$M$12 -> 0.076640209
A6: CELIMAX | B6: 1 | C6: 240 | D6: 175200 | E6: 159326.4 | F6: =D6-E6 -> 15873.6 | G6: =F6/E6 -> 0.09962944 | H6: =D6/$D$12 -> 0.064431592 | I6: =F6/$F$12 -> 0.064395254 | J6: =C6/$C$12 -> 0.039689102 | K6: =D6/C6 -> 730 | L6: 2414400 | M6: =L6*Параметры!$B$5/1000*Параметры!$B$6 -> 182673.5 | N6: =D6-M6 -> -7473.504 | O6: =N6/M6 -> -0.040911812 | P6: =M6/$M$12 -> 0.072258716
A7: JMSOLUTION | B7: 10 | C7: 400 | D7: 168400 | E7: 153234 | F7: =D7-E7 -> 15166 | G7: =F7/E7 -> 0.098972813 | H7: =D7/$D$12 -> 0.061930822 | I7: =F7/$F$12 -> 0.061524696 | J7: =C7/$C$12 -> 0.066148503 | K7: =D7/C7 -> 421 | L7: 1577600 | M7: =L7*Параметры!$B$5/1000*Параметры!$B$6 -> 119361.22 | N7: =D7-M7 -> 49038.784 | O7: =N7/M7 -> 0.41084354 | P7: =M7/$M$12 -> 0.047214774
A8: FARMSTAY | B8: 3 | C8: 400 | D8: 119900 | E8: 108872 | F8: =D8-E8 -> 11028 | G8: =F8/E8 -> 0.10129326 | H8: =D8/$D$12 -> 0.044094451 | I8: =F8/$F$12 -> 0.044737858 | J8: =C8/$C$12 -> 0.066148503 | K8: =D8/C8 -> 299.75 | L8: 1369100 | M8: =L8*Параметры!$B$5/1000*Параметры!$B$6 -> 103586.11 | N8: =D8-M8 -> 16313.894 | O8: =N8/M8 -> 0.15749114 | P8: =M8/$M$12 -> 0.040974738
A9: VT | B9: 1 | C9: 60 | D9: 88200 | E9: 80157 | F9: =D9-E9 -> 8043 | G9: =F9/E9 -> 0.10034058 | H9: =D9/$D$12 -> 0.032436452 | I9: =F9/$F$12 -> 0.032628454 | J9: =C9/$C$12 -> 0.0099222755 | K9: =D9/C9 -> 1470 | L9: 1269000 | M9: =L9*Параметры!$B$5/1000*Параметры!$B$6 -> 96012.54 | N9: =D9-M9 -> -7812.54 | O9: =N9/M9 -> -0.081369996 | P9: =M9/$M$12 -> 0.037978923
A10: JIGOTT | B10: 1 | C10: 240 | D10: 48960 | E10: 44606.4 | F10: =D10-E10 -> 4353.6 | G10: =F10/E10 -> 0.097600344 | H10: =D10/$D$12 -> 0.018005541 | I10: =F10/$F$12 -> 0.017661474 | J10: =C10/$C$12 -> 0.039689102 | K10: =D10/C10 -> 204 | L10: 468000 | M10: =L10*Параметры!$B$5/1000*Параметры!$B$6 -> 35408.88 | N10: =D10-M10 -> 13551.12 | O10: =N10/M10 -> 0.382704 | P10: =M10/$M$12 -> 0.014006411
A11: Доля по штукам показывает физический объём: логистика и сборка считаются в штуках, а не в рублях. | F11: =D11-E11 -> 0 | H11: =D11/$D$12 -> 0 | I11: =F11/$F$12 -> 0 | J11: =C11/$C$12 -> 0 | M11: =L11*Параметры!$B$5/1000*Параметры!$B$6 -> 0 | N11: =D11-M11 -> 0 | P11: =M11/$M$12 -> 0
A12: ИТОГО | B12: =SUM(B2:B11) -> 47 | C12: =SUM(C2:C11) -> 6047 | D12: =SUM(D2:D11) -> 2719163 | E12: =SUM(E2:E11) -> 2472660.4 | F12: =SUM(F2:F11) -> 246502.64 | G12: =F12/E12 -> 0.099691265 | H12: 1 | I12: 1 | J12: 1 | K12: =D12/C12 -> 449.67141 | L12: =SUM(L2:L11) -> 33413270 | M12: =SUM(M2:M11) -> 2528048 | N12: =SUM(N2:N11) -> 191114.99 | O12: =N12/M12 -> 0.075597849 | P12: 1
A14: Учётная себестоимость — колонка «по последнему приходу» из файла ОСТАТКИ на 18,08,26.
A15: Сегодняшняя — цена закупа в вонах × курс × коэффициент доставки. Курс и коэффициент на листе «Параметры».
