Workbook

Sheet Расходы на доставку
A1: Во что обойдется доставка двух контейнеров
A2: Желтое вводим сами: ставок на момент сборки файла нет. Все остальное считается. Цена килограмма отсюда идет в себестоимость каждой позиции.
A4: Расход | B4: Контейнер 1 | C4: Контейнер 2 | D4: Итого
A5: Аренда или покупка контейнера | D5: =B5+C5
A6: Фрахт Владивосток — Петербург | D6: =B6+C6
A7: Автодоставка до терминала во Владивостоке | D7: =B7+C7
A8: Погрузка, кран, такелаж | D8: =B8+C8
A9: Тара: поддоны, доска, брус, ящики | D9: =B9+C9
A10: Упаковочные материалы | D10: =B10+C10
A11: Страхование груза | D11: =B11+C11
A12: Выгрузка и автодоставка на склад в Питере | D12: =B12+C12
A13: Прочее | D13: =B13+C13
A14: ИТОГО расходов | B14: =SUM(B5:B13) | C14: =SUM(C5:C13) | D14: =SUM(D5:D13)
A16: Что везем
A17: Вес груза, кг | B17: 20000 | C17: 12553 | D17: =B17+C17
A18: Доставка за килограмм, руб | B18: =IFERROR(B14/B17,0) | C18: =IFERROR(C14/C17,0) | D18: =IFERROR(D14/D17,0)
A20: — Для сравнения: транспортная компания по распискам от 24.09.2026 обошлась в 81 руб за килограмм. Контейнер должен выйти в разы дешевле, иначе он не нужен.
A21: — Загрузка по весу: Контейнер 1 20.0 т из 20, Контейнер 2 12.6 т из 20.
A22: — Хранение в Питере в эти расходы не входит. Если арматура пролежит на складе год-два, хранение может обойтись дороже самой доставки — ставку надо узнать заранее.

Sheet Цена на складе в Питере
A1: Приемка и цена продажи на складе в Петербурге
A2: Принимаем груз по колонке «Принято», расхождение считается само. Себестоимость в Питере — цена склада плюс доставка по весу. От нее ставим цену продажи.
A4: № | B4: Контейнер | C4: Тип | D4: Диаметр | E4: Наименование | F4: Материал | G4: Состояние | H4: Отправлено, шт | I4: Принято в Питере, шт | J4: Расхождение | K4: Вес ед., кг | L4: Доставка на ед., руб | M4: Цена склада, руб | N4: Себестоимость в Питере, руб | O4: Доставка в цене | P4: Цена продажи в Питере, руб | Q4: Наценка | R4: № места | S4: Примечание
A5: 1 | B5: Контейнер 1 | C5: клинкет (задвижка) | D5: Ду250 | E5: Клинкет Ду 250 | F5: проверить: везем бронзу и латунь | H5: 2 | J5: =IF(I5="","",I5-H5) | K5: 220 | L5: =K5*'Расходы на доставку'!$B$18 | M5: 200000 | N5: =IF(M5="","",M5+L5) | O5: =IFERROR(L5/N5,"") | Q5: =IFERROR(P5/N5-1,"")
A6: 2 | B6: Контейнер 1 | C6: клинкет (задвижка) | D6: Ду250 | E6: Клинкет Ду 250 не комплект | F6: проверить: везем бронзу и латунь | H6: 2 | J6: =IF(I6="","",I6-H6) | K6: 220 | L6: =K6*'Расходы на доставку'!$B$18 | M6: 200000 | N6: =IF(M6="","",M6+L6) | O6: =IFERROR(L6/N6,"") | Q6: =IFERROR(P6/N6-1,"")
A7: 3 | B7: Контейнер 1 | C7: клинкет (задвижка) | D7: Ду300 | E7: Клинкет Ду 300 | F7: проверить: везем бронзу и латунь | H7: 16 | J7: =IF(I7="","",I7-H7) | K7: 300 | L7: =K7*'Расходы на доставку'!$B$18 | M7: 250000 | N7: =IF(M7="","",M7+L7) | O7: =IFERROR(L7/N7,"") | Q7: =IFERROR(P7/N7-1,"")
A8: 4 | B8: Контейнер 1 | C8: клинкет (задвижка) | D8: Ду350 | E8: Клинкет Ду 350 | F8: проверить: везем бронзу и латунь | H8: 1 | J8: =IF(I8="","",I8-H8) | K8: 400 | L8: =K8*'Расходы на доставку'!$B$18 | M8: 300000 | N8: =IF(M8="","",M8+L8) | O8: =IFERROR(L8/N8,"") | Q8: =IFERROR(P8/N8-1,"")
A9: 5 | B9: Контейнер 1 | C9: клинкет (задвижка) | D9: Ду250 | E9: Задвижка клинкетная Ду 250 | F9: проверить: везем бронзу и латунь | H9: 17 | J9: =IF(I9="","",I9-H9) | K9: 220 | L9: =K9*'Расходы на доставку'!$B$18 | M9: 150000 | N9: =IF(M9="","",M9+L9) | O9: =IFERROR(L9/N9,"") | Q9: =IFERROR(P9/N9-1,"")
A10: 6 | B10: Контейнер 1 | C10: клапан фланцевый | D10: Ду50 | E10: Клапан фланцевый проходной титановые Ду50Ру10 | F10: титан | H10: 5 | J10: =IF(I10="","",I10-H10) | K10: 14 | L10: =K10*'Расходы на доставку'!$B$18 | N10: =IF(M10="","",M10+L10) | O10: =IFERROR(L10/N10,"") | Q10: =IFERROR(P10/N10-1,"")
A11: 7 | B11: Контейнер 1 | C11: клапан фланцевый | D11: Ду100 | E11: Клапан фланцевый проходной титановые Ду100Ру10 | F11: титан | H11: 1 | J11: =IF(I11="","",I11-H11) | K11: 40 | L11: =K11*'Расходы на доставку'!$B$18 | N11: =IF(M11="","",M11+L11) | O11: =IFERROR(L11/N11,"") | Q11: =IFERROR(P11/N11-1,"")
A12: 8 | B12: Контейнер 1 | C12: клапан фланцевый | D12: Ду25 | E12: Клапан фланцевый угловой Ду25 | F12: бронза/латунь | H12: 15 | J12: =IF(I12="","",I12-H12) | K12: 5 | L12: =K12*'Расходы на доставку'!$B$18 | M12: 9600 | N12: =IF(M12="","",M12+L12) | O12: =IFERROR(L12/N12,"") | Q12: =IFERROR(P12/N12-1,"")
A13: 9 | B13: Контейнер 1 | C13: клапан фланцевый | D13: Ду40 | E13: Клапан фланцевый угловой Ду40 Ру25 | F13: бронза/латунь | H13: 1 | J13: =IF(I13="","",I13-H13) | K13: 10 | L13: =K13*'Расходы на доставку'!$B$18 | M13: 18000 | N13: =IF(M13="","",M13+L13) | O13: =IFERROR(L13/N13,"") | Q13: =IFERROR(P13/N13-1,"")
A14: 10 | B14: Контейнер 1 | C14: клапан фланцевый | D14: Ду50 | E14: Клапан фланцевый угловой Ду50 Ру25 | F14: бронза/латунь | H14: 7 | J14: =IF(I14="","",I14-H14) | K14: 14 | L14: =K14*'Расходы на доставку'!$B$18 | M14: 22500 | N14: =IF(M14="","",M14+L14) | O14: =IFERROR(L14/N14,"") | Q14: =IFERROR(P14/N14-1,"")
A15: 11 | B15: Контейнер 1 | C15: клапан фланцевый | D15: Ду40 | E15: Клапан фланцевый угловой Ду40 Ру10 | F15: бронза/латунь | H15: 1 | J15: =IF(I15="","",I15-H15) | K15: 10 | L15: =K15*'Расходы на доставку'!$B$18 | M15: 16000 | N15: =IF(M15="","",M15+L15) | O15: =IFERROR(L15/N15,"") | Q15: =IFERROR(P15/N15-1,"")
A16: 12 | B16: Контейнер 1 | C16: клинкет (задвижка) | D16: Ду65 | E16: Задвижка клинкетная Ду65 | F16: бронза/латунь | H16: 16 | J16: =IF(I16="","",I16-H16) | K16: 18 | L16: =K16*'Расходы на доставку'!$B$18 | M16: 27000 | N16: =IF(M16="","",M16+L16) | O16: =IFERROR(L16/N16,"") | Q16: =IFERROR(P16/N16-1,"")
A17: 13 | B17: Контейнер 1 | C17: клапан фланцевый | D17: Ду65 | E17: Клапан фланцевый угловой Ду65 Ру10 | F17: бронза/латунь | H17: 6 | J17: =IF(I17="","",I17-H17) | K17: 20 | L17: =K17*'Расходы на доставку'!$B$18 | M17: 27000 | N17: =IF(M17="","",M17+L17) | O17: =IFERROR(L17/N17,"") | Q17: =IFERROR(P17/N17-1,"")
A18: 14 | B18: Контейнер 1 | C18: клапан фланцевый | D18: Ду65 | E18: Клапан фланцевый угловой Ду65 Ру10 | F18: бронза/латунь | H18: 3 | J18: =IF(I18="","",I18-H18) | K18: 20 | L18: =K18*'Расходы на доставку'!$B$18 | M18: 27000 | N18: =IF(M18="","",M18+L18) | O18: =IFERROR(L18/N18,"") | Q18: =IFERROR(P18/N18-1,"")
A19: 15 | B19: Контейнер 1 | C19: клапан фланцевый | D19: Ду65 | E19: Клапан фланцевый угловой Ду65 Ру10 | F19: бронза/латунь | H19: 12 | J19: =IF(I19="","",I19-H19) | K19: 20 | L19: =K19*'Расходы на доставку'!$B$18 | M19: 27000 | N19: =IF(M19="","",M19+L19) | O19: =IFERROR(L19/N19,"") | Q19: =IFERROR(P19/N19-1,"")
A20: 16 | B20: Контейнер 1 | C20: клинкет (задвижка) | D20: Ду70 | E20: Задвижка клинкетная фланцевая Ду70 Ру6 | F20: бронза/латунь | H20: 7 | J20: =IF(I20="","",I20-H20) | K20: 22 | L20: =K20*'Расходы на доставку'!$B$18 | M20: 27000 | N20: =IF(M20="","",M20+L20) | O20: =IFERROR(L20/N20,"") | Q20: =IFERROR(P20/N20-1,"")
A21: 17 | B21: Контейнер 1 | C21: клапан фланцевый | D21: Ду80 | E21: Клапан фланцевый угловой Ду80 | F21: бронза/латунь | H21: 7 | J21: =IF(I21="","",I21-H21) | K21: 28 | L21: =K21*'Расходы на доставку'!$B$18 | M21: 34000 | N21: =IF(M21="","",M21+L21) | O21: =IFERROR(L21/N21,"") | Q21: =IFERROR(P21/N21-1,"")
A22: 18 | B22: Контейнер 1 | C22: клинкет (задвижка) | D22: Ду80 | E22: Задвижка клинкетная фланцевая Ду80 Ру6 | F22: бронза/латунь | H22: 18 | J22: =IF(I22="","",I22-H22) | K22: 28 | L22: =K22*'Расходы на доставку'!$B$18 | M22: 32000 | N22: =IF(M22="","",M22+L22) | O22: =IFERROR(L22/N22,"") | Q22: =IFERROR(P22/N22-1,"")
A23: 19 | B23: Контейнер 1 | C23: клинкет (задвижка) | D23: Ду60 | E23: Задвижка клинкетная Ду60 | F23: бронза/латунь | H23: 1 | J23: =IF(I23="","",I23-H23) | K23: 16 | L23: =K23*'Расходы на доставку'!$B$18 | M23: 18000 | N23: =IF(M23="","",M23+L23) | O23: =IFERROR(L23/N23,"") | Q23: =IFERROR(P23/N23-1,"")
... A29: 25 | B29: Контейнер 1 | C29: клинкет (задвижка) | D29: Ду100 | E29: Задвижка клинкетная Ду 100 БРОНЗА | F29: бронза/латунь | H29: 2 | J29: =IF(I29="","",I29-H29) | K29: 45 | L29: =K29*'Расходы на доставку'!$B$18 | M29: 35000 | N29: =IF(M29="","",M29+L29) | O29: =IFERROR(L29/N29,"") | Q29: =IFERROR(P29/N29-1,"")
A30: 26 | B30: Контейнер 1 | C30: клапан штуцерный | D30: Ду10 | E30: Клапан штуцерный угловой Ду10 Ру100 | H30: 1 | J30: =IF(I30="","",I30-H30) | K30: 0.6 | L30: =K30*'Расходы на доставку'!$B$18 | M30: 20200 | N30: =IF(M30="","",M30+L30) | O30: =IFERROR(L30/N30,"") | Q30: =IFERROR(P30/N30-1,"")
A31: 27 | B31: Контейнер 1 | C31: клапан штуцерный | D31: Ду6 | E31: Клапан предохранительный штуцерный угловой Ду6,5-9 | H31: 1 | J31: =IF(I31="","",I31-H31) | K31: 0.4 | L31: =K31*'Расходы на доставку'!$B$18 | M31: 9000 | N31: =IF(M31="","",M31+L31) | O31: =IFERROR(L31/N31,"") | Q31: =IFERROR(P31/N31-1,"")
A32: 28 | B32: Контейнер 1 | C32: клапан штуцерный | D32: Ду3 | E32: Клапан для манометра штущерный Ду3Ру400 новый | H32: 2 | J32: =IF(I32="","",I32-H32) | K32: 0.3 | L32: =K32*'Расходы на доставку'!$B$18 | M32: 6000 | N32: =IF(M32="","",M32+L32) | O32: =IFERROR(L32/N32,"") | Q32: =IFERROR(P32/N32-1,"")
A33: 29 | B33: Контейнер 1 | C33: клапан штуцерный | D33: Ду10 | E33: Клапан штуцерный проходной Ду 10 Ру40 (СУНДУК) | H33: 798 | J33: =IF(I33="","",I33-H33) | K33: 0.6 | L33: =K33*'Расходы на доставку'!$B$18 | M33: 9000 | N33: =IF(M33="","",M33+L33) | O33: =IFERROR(L33/N33,"") | Q33: =IFERROR(P33/N33-1,"")
A34: 30 | B34: Контейнер 1 | C34: клапан штуцерный | D34: Ду6 | E34: Клапан для манометра штущерный сальниковый Ду6Ру100 новый | H34: 95 | J34: =IF(I34="","",I34-H34) | K34: 0.4 | L34: =K34*'Расходы на доставку'!$B$18 | M34: 4500 | N34: =IF(M34="","",M34+L34) | O34: =IFERROR(L34/N34,"") | Q34: =IFERROR(P34/N34-1,"")
A35: 31 | B35: Контейнер 1 | C35: клапан штуцерный | D35: Ду6 | E35: Клапан для манометра штущерный сальниковый Ду6Ру100 б/у | H35: 1 | J35: =IF(I35="","",I35-H35) | K35: 0.4 | L35: =K35*'Расходы на доставку'!$B$18 | M35: 4500 | N35: =IF(M35="","",M35+L35) | O35: =IFERROR(L35/N35,"") | Q35: =IFERROR(P35/N35-1,"")
A36: 32 | B36: Контейнер 1 | C36: клапан штуцерный | D36: Ду6 | E36: Клапан для манометра штущерный сальниковый Ду6Ру100 б/у | H36: 1 | J36: =IF(I36="","",I36-H36) | K36: 0.4 | L36: =K36*'Расходы на доставку'!$B$18 | M36: 4500 | N36: =IF(M36="","",M36+L36) | O36: =IFERROR(L36/N36,"") | Q36: =IFERROR(P36/N36-1,"")
A37: 33 | B37: Контейнер 1 | C37: клапан штуцерный | D37: Ду6 | E37: Клапан предохранительный штуцерный сигнальный Ду6 Ру100-230 | H37: 1 | J37: =IF(I37="","",I37-H37) | K37: 0.4 | L37: =K37*'Расходы на доставку'!$B$18 | M37: 4500 | N37: =IF(M37="","",M37+L37) | O37: =IFERROR(L37/N37,"") | Q37: =IFERROR(P37/N37-1,"")
A38: 34 | B38: Контейнер 1 | C38: клапан штуцерный | D38: Ду6 | E38: Клапан предохранительный штуцерный сигнальный Ду6Ру100-250 | H38: 2 | J38: =IF(I38="","",I38-H38) | K38: 0.4 | L38: =K38*'Расходы на доставку'!$B$18 | M38: 4500 | N38: =IF(M38="","",M38+L38) | O38: =IFERROR(L38/N38,"") | Q38: =IFERROR(P38/N38-1,"")
A39: 35 | B39: Контейнер 1 | C39: клапан штуцерный | D39: Ду10 | E39: Клапан штуцерный проходной Ду 10 Ру400 | H39: 1 | J39: =IF(I39="","",I39-H39) | K39: 0.6 | L39: =K39*'Расходы на доставку'!$B$18 | M39: 6000 | N39: =IF(M39="","",M39+L39) | O39: =IFERROR(L39/N39,"") | Q39: =IFERROR(P39/N39-1,"")
A40: 36 | B40: Контейнер 1 | C40: клапан штуцерный | D40: Ду10 | E40: Клапан штуцерный проходной Ду 10 Ру400 | H40: 2 | J40: =IF(I40="","",I40-H40) | K40: 0.6 | L40: =K40*'Расходы на доставку'!$B$18 | M40: 6000 | N40: =IF(M40="","",M40+L40) | O40: =IFERROR(L40/N40,"") | Q40: =IFERROR(P40/N40-1,"")
A41: 37 | B41: Контейнер 1 | C41: клапан штуцерный | D41: Ду10 | E41: Клапан редукционный штуцерный угловой Ду10Ру200…30 с манометром | H41: 1 | J41: =IF(I41="","",I41-H41) | K41: 0.6 | L41: =K41*'Расходы на доставку'!$B$18 | M41: 6000 | N41: =IF(M41="","",M41+L41) | O41: =IFERROR(L41/N41,"") | Q41: =IFERROR(P41/N41-1,"")
... A126: 122 | B126: Контейнер 1 | C126: клапан штуцерный | D126: Ду10 | E126: Клапан штуцерный проходной Ду 10 | H126: 4 | J126: =IF(I126="","",I126-H126) | K126: 0.6 | L126: =K126*'Расходы на доставку'!$B$18 | M126: 2000 | N126: =IF(M126="","",M126+L126) | O126: =IFERROR(L126/N126,"") | Q126: =IFERROR(P126/N126-1,"")
A127: 123 | B127: Контейнер 1 | C127: клапан штуцерный | D127: Ду10 | E127: Клапан штуцерный проходной Ду 10 Ру25 СТАЛЬ | F127: сталь | H127: 1 | J127: =IF(I127="","",I127-H127) | K127: 0.6 | L127: =K127*'Расходы на доставку'!$B$18 | M127: 2000 | N127: =IF(M127="","",M127+L127) | O127: =IFERROR(L127/N127,"") | Q127: =IFERROR(P127/N127-1,"")
A128: 124 | B128: Контейнер 1 | C128: клапан штуцерный | D128: Ду10 | E128: Клапан штуцерный проходной Ду 10 Ру63 СТАЛЬ | F128: сталь | H128: 1 | J128: =IF(I128="","",I128-H128) | K128: 0.6 | L128: =K128*'Расходы на доставку'!$B$18 | M128: 2000 | N128: =IF(M128="","",M128+L128) | O128: =IFERROR(L128/N128,"") | Q128: =IFERROR(P128/N128-1,"")
A129: 125 | B129: Контейнер 1 | C129: клапан штуцерный | D129: Ду20 | E129: Клапан невозв-запор.цапковый угловой под дюрит Ду20Ру6 | H129: 2 | J129: =IF(I129="","",I129-H129) | K129: 1.5 | L129: =K129*'Расходы на доставку'!$B$18 | M129: 4800 | N129: =IF(M129="","",M129+L129) | O129: =IFERROR(L129/N129,"") | Q129: =IFERROR(P129/N129-1,"")
A130: 126 | B130: Контейнер 1 | C130: фильтр забортной воды | D130: Ду100 | E130: Фильтр фланц.прох. забортной воды Ду100 Ру4 | H130: 3 | J130: =IF(I130="","",I130-H130) | K130: 40 | L130: =K130*'Расходы на доставку'!$B$18 | M130: 120000 | N130: =IF(M130="","",M130+L130) | O130: =IFERROR(L130/N130,"") | Q130: =IFERROR(P130/N130-1,"")
A131: 127 | B131: Контейнер 1 | C131: фильтр забортной воды | D131: Ду100 | E131: Фильтр забортной воды Ду 100 | H131: 1 | J131: =IF(I131="","",I131-H131) | K131: 40 | L131: =K131*'Расходы на доставку'!$B$18 | M131: 120000 | N131: =IF(M131="","",M131+L131) | O131: =IFERROR(L131/N131,"") | Q131: =IFERROR(P131/N131-1,"")
A132: 128 | B132: Контейнер 1 | C132: клапан штуцерный | D132: Ду25 | E132: Клапан штуцерный угловой Ду25 | H132: 1 | J132: =IF(I132="","",I132-H132) | K132: 2.5 | L132: =K132*'Расходы на доставку'!$B$18 | M132: 7500 | N132: =IF(M132="","",M132+L132) | O132: =IFERROR(L132/N132,"") | Q132: =IFERROR(P132/N132-1,"")
A133: 129 | B133: Контейнер 1 | C133: клапан штуцерный | D133: Ду25 | E133: Клапан штуцерный угловой Ду25 | H133: 1 | J133: =IF(I133="","",I133-H133) | K133: 2.5 | L133: =K133*'Расходы на доставку'!$B$18 | M133: 7500 | N133: =IF(M133="","",M133+L133) | O133: =IFERROR(L133/N133,"") | Q133: =IFERROR(P133/N133-1,"")
A134: 130 | B134: Контейнер 1 | C134: клапан штуцерный | D134: Ду25 | E134: Клапан штуцерный угловой Ду25 | H134: 6 | J134: =IF(I134="","",I134-H134) | K134: 2.5 | L134: =K134*'Расходы на доставку'!$B$18 | M134: 7500 | N134: =IF(M134="","",M134+L134) | O134: =IFERROR(L134/N134,"") | Q134: =IFERROR(P134/N134-1,"")
A135: 131 | B135: Контейнер 1 | C135: клапан штуцерный | E135: Клапан для манометра штуцерный сальниковый | H135: 18 | J135: =IF(I135="","",I135-H135) | K135: 2 | L135: =K135*'Расходы на доставку'!$B$18 | M135: 6000 | N135: =IF(M135="","",M135+L135) | O135: =IFERROR(L135/N135,"") | Q135: =IFERROR(P135/N135-1,"")
A136: 132 | B136: Контейнер 1 | C136: клапан штуцерный | D136: Ду20 | E136: Клапан штуцерный угловой Ду20 ру 40 | H136: 1 | J136: =IF(I136="","",I136-H136) | K136: 1.5 | L136: =K136*'Расходы на доставку'!$B$18 | M136: 4500 | N136: =IF(M136="","",M136+L136) | O136: =IFERROR(L136/N136,"") | Q136: =IFERROR(P136/N136-1,"")
A137: 133 | B137: Контейнер 1 | C137: клапан штуцерный | D137: Ду20 | E137: Клапан штуцерный угловой Ду20 ру 40 | H137: 2 | J137: =IF(I137="","",I137-H137) | K137: 1.5 | L137: =K137*'Расходы на доставку'!$B$18 | M137: 4500 | N137: =IF(M137="","",M137+L137) | O137: =IFERROR(L137/N137,"") | Q137: =IFERROR(P137/N137-1,"")
A138: 134 | B138: Контейнер 1 | C138: клапан штуцерный | D138: Ду20 | E138: Клапан штуцерный угловой Ду20 ру 40 | H138: 1 | J138: =IF(I138="","",I138-H138) | K138: 1.5 | L138: =K138*'Расходы на доставку'!$B$18 | M138: 4500 | N138: =IF(M138="","",M138+L138) | O138: =IFERROR(L138/N138,"") | Q138: =IFERROR(P138/N138-1,"")
A139: 135 | B139: Контейнер 1 | C139: клапан штуцерный | D139: Ду20 | E139: Клапан штуцерный угловой Ду20 Ру160 | H139: 3 | J139: =IF(I139="","",I139-H139) | K139: 1.5 | L139: =K139*'Расходы на доставку'!$B$18 | M139: 4500 | N139: =IF(M139="","",M139+L139) | O139: =IFERROR(L139/N139,"") | Q139: =IFERROR(P139/N139-1,"")
A140: 136 | B140: Контейнер 1 | C140: клапан штуцерный | D140: Ду25 | E140: Клапан штуцерный угловой Ду25 Ру100 | H140: 8 | J140: =IF(I140="","",I140-H140) | K140: 2.5 | L140: =K140*'Расходы на доставку'!$B$18 | M140: 7500 | N140: =IF(M140="","",M140+L140) | O140: =IFERROR(L140/N140,"") | Q140: =IFERROR(P140/N140-1,"")
A141: 137 | B141: Контейнер 1 | C141: клапан штуцерный | D141: Ду25 | E141: Клапан штуцерный угловой Ду25 Ру100 | H141: 1 | J141: =IF(I141="","",I141-H141) | K141: 2.5 | L141: =K141*'Расходы на доставку'!$B$18 | M141: 7500 | N141: =IF(M141="","",M141+L141) | O141: =IFERROR(L141/N141,"") | Q141: =IFERROR(P141/N141-1,"")
A142: 138 | B142: Контейнер 1 | C142: клапан штуцерный | D142: Ду25 | E142: Клапан штуцерный угловой Ду25 Ру100 | H142: 2 | J142: =IF(I142="","",I142-H142) | K142: 2.5 | L142: =K142*'Расходы на доставку'!$B$18 | M142: 7500 | N142: =IF(M142="","",M142+L142) | O142: =IFERROR(L142/N142,"") | Q142: =IFERROR(P142/N142-1,"")
A143: 139 | B143: Контейнер 1 | C143: клапан штуцерный | D143: Ду32 | E143: Клапан штуцерный угловой Ду32Ру100 (Яшик мет.) | H143: 31 | J143: =IF(I143="","",I143-H143) | K143: 3.5 | L143: =K143*'Расходы на доставку'!$B$18 | M143: 9600 | N143: =IF(M143="","",M143+L143) | O143: =IFERROR(L143/N143,"") | Q143: =IFERROR(P143/N143-1,"")
A144: 140 | B144: Контейнер 1 | C144: клапан штуцерный | D144: Ду32 | E144: Клапан штуцерный угловой Ду32Ру100 (Яшик мет.) | H144: 14 | J144: =IF(I144="","",I144-H144) | K144: 3.5 | L144: =K144*'Расходы на доставку'!$B$18 | M144: 9600 | N144: =IF(M144="","",M144+L144) | O144: =IFERROR(L144/N144,"") | Q144: =IFERROR(P144/N144-1,"")
A145: 141 | B145: Контейнер 1 | C145: клапан штуцерный | D145: Ду32 | E145: Клапан штуцерный угловой Ду32Ру100 (Яшик мет.) | H145: 1 | J145: =IF(I145="","",I145-H145) | K145: 3.5 | L145: =K145*'Расходы на доставку'!$B$18 | M145: 9600 | N145: =IF(M145="","",M145+L145) | O145: =IFERROR(L145/N145,"") | Q145: =IFERROR(P145/N145-1,"")
A146: 142 | B146: Контейнер 1 | C146: клапан штуцерный | D146: Ду32 | E146: Клапан штуцерный угловой Ду32Ру100 (Яшик мет.) | H146: 1 | J146: =IF(I146="","",I146-H146) | K146: 3.5 | L146: =K146*'Расходы на доставку'!$B$18 | M146: 9600 | N146: =IF(M146="","",M146+L146) | O146: =IFERROR(L146/N146,"") | Q146: =IFERROR(P146/N146-1,"")
A147: 143 | B147: Контейнер 1 | C147: клапан штуцерный | D147: Ду32 | E147: Клапан штуцерный угловой Ду32 | H147: 8 | J147: =IF(I147="","",I147-H147) | K147: 3.5 | L147: =K147*'Расходы на доставку'!$B$18 | M147: 9600 | N147: =IF(M147="","",M147+L147) | O147: =IFERROR(L147/N147,"") | Q147: =IFERROR(P147/N147-1,"")
... A162: 158 | B162: Контейнер 1 | C162: фильтр забортной воды | D162: Ду200 | E162: Фильтр забортной воды Ду200 Большой | H162: 8 | J162: =IF(I162="","",I162-H162) | K162: 120 | L162: =K162*'Расходы на доставку'!$B$18 | M162: 250000 | N162: =IF(M162="","",M162+L162) | O162: =IFERROR(L162/N162,"") | Q162: =IFERROR(P162/N162-1,"")
A163: 159 | B163: Контейнер 1 | C163: прочая арматура | E163: Судовая запорная арматура | H163: 2 | J163: =IF(I163="","",I163-H163) | K163: 5 | L163: =K163*'Расходы на доставку'!$B$18 | M163: 10000 | N163: =IF(M163="","",M163+L163) | O163: =IFERROR(L163/N163,"") | Q163: =IFERROR(P163/N163-1,"")
A164: 160 | B164: Контейнер 1 | C164: фильтр забортной воды | D164: Ду150 | E164: Фильтр заборной воды ДУ 150 | H164: 5 | J164: =IF(I164="","",I164-H164) | K164: 75 | L164: =K164*'Расходы на доставку'!$B$18 | M164: 150000 | N164: =IF(M164="","",M164+L164) | O164: =IFERROR(L164/N164,"") | Q164: =IFERROR(P164/N164-1,"")
A165: 161 | B165: Контейнер 1 | C165: клапан штуцерный | D165: Ду20 | E165: Клапан штуцерный угловой Ду20 Ру100 | H165: 5 | J165: =IF(I165="","",I165-H165) | K165: 1.5 | L165: =K165*'Расходы на доставку'!$B$18 | M165: 3000 | N165: =IF(M165="","",M165+L165) | O165: =IFERROR(L165/N165,"") | Q165: =IFERROR(P165/N165-1,"")
A166: 162 | B166: Контейнер 1 | C166: клапан штуцерный | E166: Клапан штуцерный угловой Рр150/10 | H166: 8 | J166: =IF(I166="","",I166-H166) | K166: 2 | L166: =K166*'Расходы на доставку'!$B$18 | M166: 4000 | N166: =IF(M166="","",M166+L166) | O166: =IFERROR(L166/N166,"") | Q166: =IFERROR(P166/N166-1,"")
A167: 163 | B167: Контейнер 1 | C167: фильтр забортной воды | D167: Ду20 | E167: Сетка на фильтр Ду20 маленькая | H167: 1 | J167: =IF(I167="","",I167-H167) | K167: 1.5 | L167: =K167*'Расходы на доставку'!$B$18 | M167: 3000 | N167: =IF(M167="","",M167+L167) | O167: =IFERROR(L167/N167,"") | Q167: =IFERROR(P167/N167-1,"")
A168: 164 | B168: Контейнер 1 | C168: клапан фланцевый | D168: Ду32 | E168: Клапан фланцевый проходной ДУ32 Ру25 | H168: 2 | J168: =IF(I168="","",I168-H168) | K168: 7 | L168: =K168*'Расходы на доставку'!$B$18 | M168: 14000 | N168: =IF(M168="","",M168+L168) | O168: =IFERROR(L168/N168,"") | Q168: =IFERROR(P168/N168-1,"")
A169: 165 | B169: Контейнер 1 | C169: клапан фланцевый | D169: Ду32 | E169: Клапан фланцевый проходной ДУ32 Ру25 | H169: 6 | J169: =IF(I169="","",I169-H169) | K169: 7 | L169: =K169*'Расходы на доставку'!$B$18 | M169: 14000 | N169: =IF(M169="","",M169+L169) | O169: =IFERROR(L169/N169,"") | Q169: =IFERROR(P169/N169-1,"")
A170: 166 | B170: Контейнер 1 | C170: клапан фланцевый | D170: Ду32 | E170: Клапан Пожарный фланцевый угловой Ду32 | H170: 1 | J170: =IF(I170="","",I170-H170) | K170: 7 | L170: =K170*'Расходы на доставку'!$B$18 | M170: 12800 | N170: =IF(M170="","",M170+L170) | O170: =IFERROR(L170/N170,"") | Q170: =IFERROR(P170/N170-1,"")
A171: 167 | B171: Контейнер 1 | C171: клапан фланцевый | D171: Ду40 | E171: Клапан угловой фланцевый Ду 40 - БРАК | H171: 3 | J171: =IF(I171="","",I171-H171) | K171: 10 | L171: =K171*'Расходы на доставку'!$B$18 | M171: 18000 | N171: =IF(M171="","",M171+L171) | O171: =IFERROR(L171/N171,"") | Q171: =IFERROR(P171/N171-1,"")
A172: 168 | B172: Контейнер 1 | C172: прочая арматура | D172: Ду20 | E172: Клапан Ду20/10 | H172: 3 | J172: =IF(I172="","",I172-H172) | K172: 5 | L172: =K172*'Расходы на доставку'!$B$18 | M172: 9000 | N172: =IF(M172="","",M172+L172) | O172: =IFERROR(L172/N172,"") | Q172: =IFERROR(P172/N172-1,"")
A173: 169 | B173: Контейнер 1 | C173: клапан фланцевый | D173: Ду40 | E173: Клапан фланцевый угловой Ду40 Ру25 сталь ок.входа | F173: сталь | H173: 2 | J173: =IF(I173="","",I173-H173) | K173: 10 | L173: =K173*'Расходы на доставку'!$B$18 | M173: 18000 | N173: =IF(M173="","",M173+L173) | O173: =IFERROR(L173/N173,"") | Q173: =IFERROR(P173/N173-1,"")
A174: 170 | B174: Контейнер 1 | C174: клапан фланцевый | D174: Ду50 | E174: Клапан фланцевый проходной невозвратный Ду 50 РУ 25 (522-01.164) | H174: 1 | J174: =IF(I174="","",I174-H174) | K174: 14 | L174: =K174*'Расходы на доставку'!$B$18 | M174: 25000 | N174: =IF(M174="","",M174+L174) | O174: =IFERROR(L174/N174,"") | Q174: =IFERROR(P174/N174-1,"")
A175: 171 | B175: Контейнер 1 | C175: клапан фланцевый | D175: Ду50 | E175: Клапан Пожарный фланцевый угловой Ду50 Ру16 | H175: 3 | J175: =IF(I175="","",I175-H175) | K175: 14 | L175: =K175*'Расходы на доставку'!$B$18 | M175: 25000 | N175: =IF(M175="","",M175+L175) | O175: =IFERROR(L175/N175,"") | Q175: =IFERROR(P175/N175-1,"")
A176: 172 | B176: Контейнер 1 | C176: клапан фланцевый | D176: Ду50 | E176: Клапан Пожарный фланцевый угловой Ду50 Ру16 | H176: 1 | J176: =IF(I176="","",I176-H176) | K176: 14 | L176: =K176*'Расходы на доставку'!$B$18 | M176: 25000 | N176: =IF(M176="","",M176+L176) | O176: =IFERROR(L176/N176,"") | Q176: =IFERROR(P176/N176-1,"")
A177: 173 | B177: Контейнер 1 | C177: клапан фланцевый | D177: Ду50 | E177: Клапан Пожарный фланцевый угловой Ду50 Ру16 | H177: 2 | J177: =IF(I177="","",I177-H177) | K177: 14 | L177: =K177*'Расходы на доставку'!$B$18 | M177: 25000 | N177: =IF(M177="","",M177+L177) | O177: =IFERROR(L177/N177,"") | Q177: =IFERROR(P177/N177-1,"")
A178: 174 | B178: Контейнер 1 | C178: коробка клапанная | D178: Ду80 | E178: Коробка 3-х клап.фланцевая невозврат.Ду80 Ру6 | H178: 6 | J178: =IF(I178="","",I178-H178) | K178: 45 | L178: =K178*'Расходы на доставку'!$B$18 | M178: 80000 | N178: =IF(M178="","",M178+L178) | O178: =IFERROR(L178/N178,"") | Q178: =IFERROR(P178/N178-1,"")
A179: 175 | B179: Контейнер 1 | C179: клапан фланцевый | D179: Ду65 | E179: Клапан быстрозапор. фланц.проход.с тросиков.приводом Ду65 Ру6,3 | H179: 1 | J179: =IF(I179="","",I179-H179) | K179: 20 | L179: =K179*'Расходы на доставку'!$B$18 | M179: 35000 | N179: =IF(M179="","",M179+L179) | O179: =IFERROR(L179/N179,"") | Q179: =IFERROR(P179/N179-1,"")
A180: 176 | B180: Контейнер 1 | C180: клапан фланцевый | D180: Ду70 | E180: Клапан быстрозапор. фланц.проход.с тросиков.приводом Ду70 Ру6,3 | H180: 3 | J180: =IF(I180="","",I180-H180) | K180: 23 | L180: =K180*'Расходы на доставку'!$B$18 | M180: 40000 | N180: =IF(M180="","",M180+L180) | O180: =IFERROR(L180/N180,"") | Q180: =IFERROR(P180/N180-1,"")
A181: 177 | B181: Контейнер 1 | C181: клапан штуцерный | D181: Ду20 | E181: Клапан муфтовый проходной запорный Ду20Ру16 | H181: 1 | J181: =IF(I181="","",I181-H181) | K181: 1.5 | L181: =K181*'Расходы на доставку'!$B$18 | M181: 1000 | N181: =IF(M181="","",M181+L181) | O181: =IFERROR(L181/N181,"") | Q181: =IFERROR(P181/N181-1,"")
A182: 178 | B182: Контейнер 1 | C182: клапан штуцерный | D182: Ду32 | E182: Клапан муфтовый проходной запорный Ду32Ру10 | H182: 1 | J182: =IF(I182="","",I182-H182) | K182: 3.5 | L182: =K182*'Расходы на доставку'!$B$18 | M182: 1500 | N182: =IF(M182="","",M182+L182) | O182: =IFERROR(L182/N182,"") | Q182: =IFERROR(P182/N182-1,"")
A183: 179 | B183: Контейнер 1 | C183: клапан штуцерный | D183: Ду15 | E183: (Кнопка)Клапан самозакрывающий проходной муфтовый Ду15Ру3 | H183: 1 | J183: =IF(I183="","",I183-H183) | K183: 1 | L183: =K183*'Расходы на доставку'!$B$18 | N183: =IF(M183="","",M183+L183) | O183: =IFERROR(L183/N183,"") | Q183: =IFERROR(P183/N183-1,"")
A184: 180 | B184: Контейнер 2 | C184: клапан фланцевый | D184: Ду65 | E184: Клапан быстрозапор. фланц. проход. с тросиков. приводом Ду65Ру6,3 | H184: 5 | J184: =IF(I184="","",I184-H184) | K184: 20 | L184: =K184*'Расходы на доставку'!$C$18 | M184: 35000 | N184: =IF(M184="","",M184+L184) | O184: =IFERROR(L184/N184,"") | Q184: =IFERROR(P184/N184-1,"")
A185: 181 | B185: Контейнер 2 | C185: клапан фланцевый | D185: Ду80 | E185: Клапан быстрозапор. фланц.проход.с тросиков.приводом Ду80 Ру6,3 | H185: 2 | J185: =IF(I185="","",I185-H185) | K185: 28 | L185: =K185*'Расходы на доставку'!$C$18 | M185: 45000 | N185: =IF(M185="","",M185+L185) | O185: =IFERROR(L185/N185,"") | Q185: =IFERROR(P185/N185-1,"")
A186: 182 | B186: Контейнер 2 | C186: клапан фланцевый | D186: Ду50 | E186: Клапан фланцевый проходной Ду50 | H186: 66 | J186: =IF(I186="","",I186-H186) | K186: 14 | L186: =K186*'Расходы на доставку'!$C$18 | M186: 22500 | N186: =IF(M186="","",M186+L186) | O186: =IFERROR(L186/N186,"") | Q186: =IFERROR(P186/N186-1,"")
A187: 183 | B187: Контейнер 2 | C187: клапан фланцевый | D187: Ду50 | E187: Клапан фланцевый проходной Ду50 Ру25 | H187: 5 | J187: =IF(I187="","",I187-H187) | K187: 14 | L187: =K187*'Расходы на доставку'!$C$18 | M187: 22500 | N187: =IF(M187="","",M187+L187) | O187: =IFERROR(L187/N187,"") | Q187: =IFERROR(P187/N187-1,"")
A188: 184 | B188: Контейнер 2 | C188: клапан фланцевый | D188: Ду50 | E188: Клапан Пожарный фланцевый проходной Ду50 Ру16 | H188: 2 | J188: =IF(I188="","",I188-H188) | K188: 14 | L188: =K188*'Расходы на доставку'!$C$18 | M188: 22500 | N188: =IF(M188="","",M188+L188) | O188: =IFERROR(L188/N188,"") | Q188: =IFERROR(P188/N188-1,"")
A189: 185 | B189: Контейнер 2 | C189: захлопка | D189: Ду50 | E189: Захлопка Ду50Ру6 - БРАК | H189: 3 | J189: =IF(I189="","",I189-H189) | K189: 12 | L189: =K189*'Расходы на доставку'!$C$18 | M189: 17500 | N189: =IF(M189="","",M189+L189) | O189: =IFERROR(L189/N189,"") | Q189: =IFERROR(P189/N189-1,"")
A190: 186 | B190: Контейнер 2 | C190: клапан фланцевый | D190: Ду50 | E190: Клапан фланцевый проходной Ду50 Ру 10 + ДУ 50 Ру 25 | H190: 98 | J190: =IF(I190="","",I190-H190) | K190: 14 | L190: =K190*'Расходы на доставку'!$C$18 | M190: 20000 | N190: =IF(M190="","",M190+L190) | O190: =IFERROR(L190/N190,"") | Q190: =IFERROR(P190/N190-1,"")
A191: 187 | B191: Контейнер 2 | C191: клапан фланцевый | D191: Ду32 | E191: Клапан проходной фланцевый Ду32 - БРАК | H191: 6 | J191: =IF(I191="","",I191-H191) | K191: 7 | L191: =K191*'Расходы на доставку'!$C$18 | M191: 10000 | N191: =IF(M191="","",M191+L191) | O191: =IFERROR(L191/N191,"") | Q191: =IFERROR(P191/N191-1,"")
A192: 188 | B192: Контейнер 2 | C192: клапан штуцерный | D192: Ду50 | E192: Клапан угловой с присоединением под дюрит Ду50Ру4 | H192: 4 | J192: =IF(I192="","",I192-H192) | K192: 7 | L192: =K192*'Расходы на доставку'!$C$18 | M192: 10000 | N192: =IF(M192="","",M192+L192) | O192: =IFERROR(L192/N192,"") | Q192: =IFERROR(P192/N192-1,"")
A193: 189 | B193: Контейнер 2 | C193: клапан штуцерный | D193: Ду50 | E193: Клапан невозв-запорн.с присоед.под дюрит прох. Ду 50 Ру6 | H193: 1 | J193: =IF(I193="","",I193-H193) | K193: 7 | L193: =K193*'Расходы на доставку'!$C$18 | M193: 10000 | N193: =IF(M193="","",M193+L193) | O193: =IFERROR(L193/N193,"") | Q193: =IFERROR(P193/N193-1,"")
A194: 190 | B194: Контейнер 2 | C194: коробка клапанная | D194: Ду50 | E194: Коробка 2-х клапановая фланцевая Ду50 | H194: 4 | J194: =IF(I194="","",I194-H194) | K194: 25 | L194: =K194*'Расходы на доставку'!$C$18 | M194: 35000 | N194: =IF(M194="","",M194+L194) | O194: =IFERROR(L194/N194,"") | Q194: =IFERROR(P194/N194-1,"")
A195: 191 | B195: Контейнер 2 | C195: клапан фланцевый | D195: Ду32 | E195: Клапан предохранит. фланцевый угловой Ду32Ру4 (524-03.090) | H195: 1 | J195: =IF(I195="","",I195-H195) | K195: 7 | L195: =K195*'Расходы на доставку'!$C$18 | M195: 9600 | N195: =IF(M195="","",M195+L195) | O195: =IFERROR(L195/N195,"") | Q195: =IFERROR(P195/N195-1,"")
A196: 192 | B196: Контейнер 2 | C196: клапан фланцевый | D196: Ду32 | E196: Клапан фланцевый проходной ДУ32 Ру25 (сталь) | F196: сталь | H196: 1 | J196: =IF(I196="","",I196-H196) | K196: 7 | L196: =K196*'Расходы на доставку'!$C$18 | M196: 9600 | N196: =IF(M196="","",M196+L196) | O196: =IFERROR(L196/N196,"") | Q196: =IFERROR(P196/N196-1,"")
A197: 193 | B197: Контейнер 2 | C197: клапан фланцевый | D197: Ду65 | E197: Клапан фланцевый проходной Ду65 | H197: 25 | J197: =IF(I197="","",I197-H197) | K197: 20 | L197: =K197*'Расходы на доставку'!$C$18 | M197: 27000 | N197: =IF(M197="","",M197+L197) | O197: =IFERROR(L197/N197,"") | Q197: =IFERROR(P197/N197-1,"")
A198: 194 | B198: Контейнер 2 | C198: клапан фланцевый | D198: Ду65 | E198: Клапан фланцевый проходной Ду65 Ру10 | H198: 1 | J198: =IF(I198="","",I198-H198) | K198: 20 | L198: =K198*'Расходы на доставку'!$C$18 | M198: 27000 | N198: =IF(M198="","",M198+L198) | O198: =IFERROR(L198/N198,"") | Q198: =IFERROR(P198/N198-1,"")
A199: 195 | B199: Контейнер 2 | C199: коробка клапанная | D199: Ду80 | E199: Коробка 2-х клапановая фланцевая Ду80 | H199: 2 | J199: =IF(I199="","",I199-H199) | K199: 45 | L199: =K199*'Расходы на доставку'!$C$18 | M199: 60000 | N199: =IF(M199="","",M199+L199) | O199: =IFERROR(L199/N199,"") | Q199: =IFERROR(P199/N199-1,"")
A200: 196 | B200: Контейнер 2 | C200: клапан фланцевый | D200: Ду70 | E200: Клапан фланцевый проходной Ду70 Ру10 | H200: 5 | J200: =IF(I200="","",I200-H200) | K200: 23 | L200: =K200*'Расходы на доставку'!$C$18 | M200: 30000 | N200: =IF(M200="","",M200+L200) | O200: =IFERROR(L200/N200,"") | Q200: =IFERROR(P200/N200-1,"")
A201: 197 | B201: Контейнер 2 | C201: клапан фланцевый | D201: Ду70 | E201: Клапан фланцевый проходной Ду70 Ру10 | H201: 2 | J201: =IF(I201="","",I201-H201) | K201: 23 | L201: =K201*'Расходы на доставку'!$C$18 | M201: 30000 | N201: =IF(M201="","",M201+L201) | O201: =IFERROR(L201/N201,"") | Q201: =IFERROR(P201/N201-1,"")
A202: 198 | B202: Контейнер 2 | C202: клапан фланцевый | D202: Ду50 | E202: Клапан проходной фланцевый Ду50 - БРАК | H202: 8 | J202: =IF(I202="","",I202-H202) | K202: 14 | L202: =K202*'Расходы на доставку'!$C$18 | M202: 18000 | N202: =IF(M202="","",M202+L202) | O202: =IFERROR(L202/N202,"") | Q202: =IFERROR(P202/N202-1,"")
A203: 199 | B203: Контейнер 2 | C203: клапан фланцевый | D203: Ду80 | E203: Клапан фланцевый проходной Ду80 | H203: 6 | J203: =IF(I203="","",I203-H203) | K203: 28 | L203: =K203*'Расходы на доставку'!$C$18 | M203: 36000 | N203: =IF(M203="","",M203+L203) | O203: =IFERROR(L203/N203,"") | Q203: =IFERROR(P203/N203-1,"")
A204: 200 | B204: Контейнер 2 | C204: клинкет (задвижка) | E204: Электропривод к задвижке | H204: 1 | J204: =IF(I204="","",I204-H204) | K204: 40 | L204: =K204*'Расходы на доставку'!$C$18 | M204: 50000 | N204: =IF(M204="","",M204+L204) | O204: =IFERROR(L204/N204,"") | Q204: =IFERROR(P204/N204-1,"")
...

Sheet Итоги по складу
A1: Что лежит на складе в Питере и сколько это стоит
A2: Считается по листу цены. Пока приемка не заполнена, часть строк будет пустой.
A4: По контейнерам
A5: Контейнер | B5: Позиций | C5: Отправлено, шт | D5: Принято, шт | E5: Цена склада, руб | F5: Доставка, руб | G5: Себестоимость в Питере, руб
A6: Контейнер 1 | B6: =COUNTIF('Цена на складе в Питере'!$B$5:$B$274,"Контейнер 1") | C6: =SUMIF('Цена на складе в Питере'!$B$5:$B$274,"Контейнер 1",'Цена на складе в Питере'!$H$5:$H$274) | D6: =SUMIF('Цена на складе в Питере'!$B$5:$B$274,"Контейнер 1",'Цена на складе в Питере'!$I$5:$I$274) | E6: =SUMPRODUCT(('Цена на складе в Питере'!$B$5:$B$274="Контейнер 1")*IFERROR('Цена на складе в Питере'!$H$5:$H$274*'Цена на складе в Питере'!$M$5:$M$274,0)) | F6: =SUMPRODUCT(('Цена на складе в Питере'!$B$5:$B$274="Контейнер 1")*IFERROR('Цена на складе в Питере'!$H$5:$H$274*'Цена на складе в Питере'!$L$5:$L$274,0)) | G6: =E6+F6
A7: Контейнер 2 | B7: =COUNTIF('Цена на складе в Питере'!$B$5:$B$274,"Контейнер 2") | C7: =SUMIF('Цена на складе в Питере'!$B$5:$B$274,"Контейнер 2",'Цена на складе в Питере'!$H$5:$H$274) | D7: =SUMIF('Цена на складе в Питере'!$B$5:$B$274,"Контейнер 2",'Цена на складе в Питере'!$I$5:$I$274) | E7: =SUMPRODUCT(('Цена на складе в Питере'!$B$5:$B$274="Контейнер 2")*IFERROR('Цена на складе в Питере'!$H$5:$H$274*'Цена на складе в Питере'!$M$5:$M$274,0)) | F7: =SUMPRODUCT(('Цена на складе в Питере'!$B$5:$B$274="Контейнер 2")*IFERROR('Цена на складе в Питере'!$H$5:$H$274*'Цена на складе в Питере'!$L$5:$L$274,0)) | G7: =E7+F7
A8: ИТОГО | B8: =SUM(B6:B7) | C8: =SUM(C6:C7) | D8: =SUM(D6:D7) | E8: =SUM(E6:E7) | F8: =SUM(F6:F7) | G8: =SUM(G6:G7)
A10: Приемка
A11: Строк принято | B11: =COUNT('Цена на складе в Питере'!$I$5:$I$274)
A12: Строк осталось принять | B12: =COUNTA('Цена на складе в Питере'!$E$5:$E$274)-COUNT('Цена на складе в Питере'!$I$5:$I$274)
A13: Расхождение всего, шт | B13: =SUM('Цена на складе в Питере'!$J$5:$J$274)
A14: Строк с расхождением | B14: =COUNTIF('Цена на складе в Питере'!$J$5:$J$274,"<>0")-COUNTBLANK('Цена на складе в Питере'!$J$5:$J$274)

Sheet Как работать с файлом
A1: Порядок работы
A3: № | B3: Правило | C3: Почему так
A4: 1 | B4: Сначала расходы, потом цены | C4: Пока на листе расходов нули, доставка на единицу будет нулевой, и себестоимость в Питере совпадет с ценой склада. Ставить цену продажи от такой цифры нельзя.
A5: 2 | B5: Принимаем по местам, а не по памяти | C5: Номер места в этой таблице должен совпадать с биркой на ящике и строкой упаковочного листа. Расхождение фиксируем в день выгрузки, иначе повторим владивостокскую историю с недостоверными остатками.
A6: 3 | B6: Состояние переносим из отгрузки | C6: Новое и б/у на питерском складе продаются по разной цене. Если состояние не проставили при погрузке, на приемке это уже спорно.
A7: 4 | B7: Цена продажи считается от себестоимости в Питере | C7: Это цена склада плюс доставка. На тяжелой арматуре доставка заметна, на мелочи почти нет — поэтому наценку ставим по строке, а не одним процентом на весь склад.
A8: 5 | B8: Хранение считаем отдельно | C8: Доставка — разовый расход, хранение идет каждый месяц. Если арматура лежит год-два, хранение способно перекрыть доставку. Ставку за квадратный метр или за паллетоместо надо знать до того, как контейнеры выехали.
A9: 6 | B9: Позиции без цены не продаем вслепую | C9: В складских файлах часть позиций идет без цены. Пока цена не проставлена, себестоимость в Питере по ним не считается.
